lab2.1/gate.v
module gate(doorOpen, fiveMinTillArriv, diffOk, whatGate, poundOccu, reset);
	output doorOpen;
	input fiveMinTillArriv, diffOk, whatGate, poundOccu, reset;
	
	assign doorOpen = (~whatGate && poundOccu && diffOk) || (whatGate && diffOk && ~poundOccu && fiveMinTillArriv);	
endmodule

lab2.1/gate_testbench.v
`include "gate.v"
module gate_testbench;
	wire doorOpen;
	reg fiveMinTillArriv, diffOk, whatGate, poundOccu, reset; 	
	
	gate dut(.doorOpen(doorOpen), .fiveMinTillArriv(fiveMinTillArriv), .diffOk(diffOk), .whatGate(whatGate), .poundOccu(poundOccu), .reset(reset)); 
	
	parameter delay = 10; 
	initial begin
		reset = 0; #delay;
		reset = 1; #delay;

		$display("whatGate poundOccu 5minTA diffOk ");
		$monitor("%b\t %b\t  %b\t  %b\t %b\t", whatGate, poundOccu, fiveMinTillArriv, diffOk, doorOpen);
		
		whatGate = 0; poundOccu = 0; fiveMinTillArriv = 0; diffOk = 0; #delay;
		whatGate = 0; poundOccu = 0; fiveMinTillArriv = 0; diffOk = 1; #delay;
		whatGate = 0; poundOccu = 0; fiveMinTillArriv = 1; diffOk = 0; #delay;
		whatGate = 0; poundOccu = 0; fiveMinTillArriv = 1; diffOk = 1; #delay;
		whatGate = 0; poundOccu = 1; fiveMinTillArriv = 0; diffOk = 0; #delay;
		whatGate = 0; poundOccu = 1; fiveMinTillArriv = 0; diffOk = 1; #delay;
		whatGate = 0; poundOccu = 1; fiveMinTillArriv = 1; diffOk = 0; #delay;
		whatGate = 0; poundOccu = 1; fiveMinTillArriv = 1; diffOk = 1; #delay;
		whatGate = 1; poundOccu = 0; fiveMinTillArriv = 0; diffOk = 0; #delay;
		whatGate = 1; poundOccu = 0; fiveMinTillArriv = 0; diffOk = 1; #delay;
		whatGate = 1; poundOccu = 0; fiveMinTillArriv = 1; diffOk = 0; #delay;
		whatGate = 1; poundOccu = 0; fiveMinTillArriv = 1; diffOk = 1; #delay;
		whatGate = 1; poundOccu = 1; fiveMinTillArriv = 0; diffOk = 0; #delay;
		whatGate = 1; poundOccu = 1; fiveMinTillArriv = 0; diffOk = 1; #delay;
		whatGate = 1; poundOccu = 1; fiveMinTillArriv = 1; diffOk = 0; #delay;
		whatGate = 1; poundOccu = 1; fiveMinTillArriv = 1; diffOk = 1; #delay;
			
 		$finish; // finish simulation
	end 
	
	// file for gtkwave
	initial begin
		$dumpfile("gate.vcd");
		$dumpvars;
	end
endmodule

jun/gate.vcd
$date
	Thu Oct 27 09:57:44 2016
$end
$version
	Icarus Verilog
$end
$timescale
	1s
$end
$scope module gate_testbench $end
$var wire 1 ! doorOpen $end
$var reg 1 " diffOk $end
$var reg 1 # fiveMinTillArriv $end
$var reg 1 $ poundOccu $end
$var reg 1 % reset $end
$var reg 1 & whatGate $end
$scope module dut $end
$var wire 1 " diffOk $end
$var wire 1 ! doorOpen $end
$var wire 1 # fiveMinTillArriv $end
$var wire 1 $ poundOccu $end
$var wire 1 % reset $end
$var wire 1 & whatGate $end
$upscope $end
$upscope $end
$enddefinitions $end
#0
$dumpvars
x&
0%
x$
x#
x"
x!
$end
#10
1%
#20
0!
0"
0#
0$
0&
#30
1"
#40
0"
1#
#50
1"
#60
0"
0#
1$
#70
1!
1"
#80
0!
0"
1#
#90
1!
1"
#100
0!
0"
0#
0$
1&
#110
1"
#120
0!
0"
1#
#130
1!
1"
#140
0!
0"
0#
1$
#150
1"
#160
0"
1#
#170
1"
