lab5/verilog/bic.v
// bit identifier count
// once the start bit has been detected (enable), counts the number of input bits that have
// been read (10 total). outputs the index of the bit being read
// enable <= 0 sets the count back to 0
module bic(nextChar, whichBit, enable, clk, rst);
	input clk, rst;				// bsc bit clk, KEY0 rst
	input enable;				// reading in frame, so count bits
	output nextChar;			// reading the stop bit

	// 4-bit counter to count clock cycles; indicates which bit is currently being read
	// clock set to posedge at the middle of the samples (bsc at 4'b0111)
	// counts 0-9 then loops back to 0 (10-bit frame)
	output reg [3:0] whichBit;
	initial whichBit = 0;

	always@(posedge clk) begin
		if(rst) whichBit <= 0;
		else begin
			if(enable) begin
				if (whichBit < 9) whichBit <= whichBit + 1'b1;	// maxes out at 10-bits
				else whichBit <= 0;								// loops back to 0
			end else whichBit <= 0;
		end
	end

	// output logic
	assign nextChar = (whichBit == 9); // currently reading the stop bit
endmodule

lab5/verilog/bic_testbench.v
// testbench for bic module
`include "bic.v"
module bic_testbench();
	reg clk, rst;
	reg enable;
	wire nextChar;
	wire [3:0] whichBit;

	// device under test
	bic dut (.nextChar(nextChar), .whichBit(whichBit), .enable(enable), .clk(clk), .rst(rst));

	// set up clock
	parameter PERIOD = 10;
	initial clk = 0;
	always begin
		#(PERIOD/2);
		clk = ~clk;
	end

	// begin simulation
	initial begin
		rst <= 1;					@(posedge clk);
		rst <= 0;	enable <= 1;	@(posedge clk);
									@(posedge clk);
									@(posedge clk);
									@(posedge clk);
									@(posedge clk);
									@(posedge clk);
									@(posedge clk);
									@(posedge clk);
									@(posedge clk);
									@(posedge clk); // 9
									@(posedge clk); // 0
					enable <= 0;	@(posedge clk); // no more data, go back to 0
									@(posedge clk);

		$finish;
	end

	// gtkwave filedump
	initial begin
		$dumpfile("bic.vcd");
		$dumpvars;
	end
endmodule

lab5/verilog/bic.vcd
$date
	Fri Dec  2 11:16:56 2016
$end
$version
	Icarus Verilog
$end
$timescale
	1s
$end
$scope module bic_testbench $end
$var wire 4 ! whichBit [3:0] $end
$var wire 1 " nextChar $end
$var reg 1 # clk $end
$var reg 1 $ enable $end
$var reg 1 % rst $end
$scope module dut $end
$var wire 1 # clk $end
$var wire 1 $ enable $end
$var wire 1 % rst $end
$var wire 1 " nextChar $end
$var reg 4 & whichBit [3:0] $end
$upscope $end
$upscope $end
$enddefinitions $end
#0
$dumpvars
b0 &
1%
x$
0#
0"
b0 !
$end
#5
1$
0%
1#
#10
0#
#15
b1 !
b1 &
1#
#20
0#
#25
b10 !
b10 &
1#
#30
0#
#35
b11 !
b11 &
1#
#40
0#
#45
b100 !
b100 &
1#
#50
0#
#55
b101 !
b101 &
1#
#60
0#
#65
b110 !
b110 &
1#
#70
0#
#75
b111 !
b111 &
1#
#80
0#
#85
b1000 !
b1000 &
1#
#90
0#
#95
1"
b1001 !
b1001 &
1#
#100
0#
#105
0"
b0 !
b0 &
1#
#110
0#
#115
0$
b1 !
b1 &
1#
#120
0#
#125
b0 !
b0 &
1#
