lab5/verilog/bsc.v
// bit sampling count
// once the start bit has been detected (enable), counts the number of samples of the input
// bit that have been received (16 total). outputs whether currently at the start, middle,
// end, or insignificant part of the bit
// enable <= 0 sets the count back to 0
module bsc(bitProgress, enable, clk, rst);
	input clk, rst;				// 16xdata rate clock, KEY0 rst
	input enable;				// reading in frame, so count bits
	output [3:0] bitProgress;	// which part of the bit

	// 4-bit counter to count samples (16 samples per bit)
	// at the start of the bit, the counter is at 4'b0000 (0)
	// in the middle of the bit, the counter is at 4'b0111 (7)
	// at the end of the bit, the counter is at 4'b1111 (15)
	reg [3:0] count;
	initial count = 0;

	always@(posedge clk) begin
		if(rst) begin
			count <= 0;
		end else begin
			if(enable) count <= count + 1'b1;
			else count <= 0;
		end
	end

	// output logic
	assign bitProgress = count;
endmodule

lab5/verilog/bsc_testbench.v
// testbench for bsc module
`include "bsc.v"
module bsc_testbench();
	reg clk, rst, enable;
	wire [3:0] bitProgress;

	// device under test
	bsc dut (.bitProgress(bitProgress), .enable(enable), .clk(clk), .rst(rst));

	// set up clock
	parameter PERIOD = 10;
	initial clk = 0;
	always begin
		#(PERIOD/2);
		clk = ~clk;
	end

	// begin simulation
	initial begin
		rst <= 1;					@(posedge clk);
		rst <= 0;	enable <= 0;	@(posedge clk); 
					enable <= 1;	@(posedge clk); // 0
									@(posedge clk);
									@(posedge clk);
									@(posedge clk);
									@(posedge clk);
									@(posedge clk); // 5
									@(posedge clk);
									@(posedge clk);
									@(posedge clk); 
									@(posedge clk);
									@(posedge clk); // 10
									@(posedge clk);
									@(posedge clk);
									@(posedge clk);
									@(posedge clk);
									@(posedge clk); // 15
									@(posedge clk); // 0
					enable <= 0;	@(posedge clk);
					enable <= 1;	@(posedge clk); // 0
		rst <= 1;					@(posedge clk); // 0
									@(posedge clk);
		$finish;
	end

	// gtkwave filedump
	initial begin
		$dumpfile("bsc.vcd");
		$dumpvars;
	end
endmodule

lab5/verilog/bsc.vcd
$date
	Fri Dec  2 00:56:53 2016
$end
$version
	Icarus Verilog
$end
$timescale
	1s
$end
$scope module bsc_testbench $end
$var wire 4 ! bitProgress [3:0] $end
$var reg 1 " clk $end
$var reg 1 # enable $end
$var reg 1 $ rst $end
$scope module dut $end
$var wire 4 % bitProgress [3:0] $end
$var wire 1 " clk $end
$var wire 1 # enable $end
$var wire 1 $ rst $end
$var reg 4 & count [3:0] $end
$upscope $end
$upscope $end
$enddefinitions $end
#0
$dumpvars
b0 &
b0 %
1$
x#
0"
b0 !
$end
#5
0#
0$
1"
#10
0"
#15
1#
1"
#20
0"
#25
b1 !
b1 %
b1 &
1"
#30
0"
#35
b10 !
b10 %
b10 &
1"
#40
0"
#45
b11 !
b11 %
b11 &
1"
#50
0"
#55
b100 !
b100 %
b100 &
1"
#60
0"
#65
b101 !
b101 %
b101 &
1"
#70
0"
#75
b110 !
b110 %
b110 &
1"
#80
0"
#85
b111 !
b111 %
b111 &
1"
#90
0"
#95
b1000 !
b1000 %
b1000 &
1"
#100
0"
#105
b1001 !
b1001 %
b1001 &
1"
#110
0"
#115
b1010 !
b1010 %
b1010 &
1"
#120
0"
#125
b1011 !
b1011 %
b1011 &
1"
#130
0"
#135
b1100 !
b1100 %
b1100 &
1"
#140
0"
#145
b1101 !
b1101 %
b1101 &
1"
#150
0"
#155
b1110 !
b1110 %
b1110 &
1"
#160
0"
#165
b1111 !
b1111 %
b1111 &
1"
#170
0"
#175
b0 !
b0 %
b0 &
1"
#180
0"
#185
b1 !
b1 %
b1 &
0#
1"
#190
0"
#195
1#
b0 !
b0 %
b0 &
1"
#200
0"
#205
b1 !
b1 %
b1 &
1$
1"
#210
0"
#215
b0 !
b0 %
b0 &
1"
