lab5/lab5/verilog/SPS_interface/bic.v
// bit identification count
// counts bits received and signals when frame has reached end
module bic(frameProgress, endFrame, enable, clk, rst);
	input	clk, rst,	// bit_clk
			enable;
	output endFrame;

	parameter FRAME_WIDTH = 10;

	output reg [3:0] frameProgress;
	initial frameProgress = 0;
	
	always@(posedge clk) begin
		if (rst) frameProgress <= 0;
		else begin
			if (enable) frameProgress <= frameProgress + 1'b1;
			else frameProgress <= 0;
		end
	end

	assign endFrame = (frameProgress == FRAME_WIDTH - 1);
endmodule

lab5/lab5/verilog/SPS_interface/bic_testbench.v
module bic_testbench();
	reg		clk, rst,
			enable;
	wire	endFrame;
	wire [3:0] frameProgress;

	// set up clock
	parameter PERIOD = 10;
	initial clk = 0;
	always begin
		#(PERIOD/2);
		clk = ~clk;
	end

	bic #(11) dut (.frameProgress(frameProgress), .endFrame(endFrame), .enable(enable), .clk(clk), .rst(rst));

	// begin simulation
	initial begin
		rst <= 1;					@(posedge clk);
		rst <= 0;	enable <= 0;	@(posedge clk);
					enable <= 1;	@(posedge clk); // 0
									@(posedge clk);
									@(posedge clk);
									@(posedge clk);
									@(posedge clk);
									@(posedge clk); // 5
									@(posedge clk);
									@(posedge clk);
									@(posedge clk);
									@(posedge clk);
									@(posedge clk); // 10
									@(posedge clk);
					enable <= 0;	@(posedge clk);
									@(posedge clk);
		$finish;
	end

	// gtkwave filedump
	initial begin
		$dumpfile("bic.vcd");
		$dumpvars;
	end
endmodule

lab5/lab5/verilog/SPS_interface/bic.vcd
$date
	Tue Dec  6 11:31:50 2016
$end
$version
	Icarus Verilog
$end
$timescale
	1s
$end
$scope module bic_testbench $end
$var wire 4 ! frameProgress [3:0] $end
$var wire 1 " endFrame $end
$var reg 1 # clk $end
$var reg 1 $ enable $end
$var reg 1 % rst $end
$scope module dut $end
$var wire 1 # clk $end
$var wire 1 $ enable $end
$var wire 1 % rst $end
$var wire 1 " endFrame $end
$var reg 4 & frameProgress [3:0] $end
$upscope $end
$upscope $end
$enddefinitions $end
#0
$dumpvars
bx &
1%
x$
0#
x"
bx !
$end
#5
0"
b0 !
b0 &
0$
0%
1#
#10
0#
#15
1$
1#
#20
0#
#25
b1 !
b1 &
1#
#30
0#
#35
b10 !
b10 &
1#
#40
0#
#45
b11 !
b11 &
1#
#50
0#
#55
b100 !
b100 &
1#
#60
0#
#65
b101 !
b101 &
1#
#70
0#
#75
b110 !
b110 &
1#
#80
0#
#85
b111 !
b111 &
1#
#90
0#
#95
b1000 !
b1000 &
1#
#100
0#
#105
b1001 !
b1001 &
1#
#110
0#
#115
1"
b1010 !
b1010 &
1#
#120
0#
#125
0"
b1011 !
b1011 &
1#
#130
0#
#135
0$
b1100 !
b1100 &
1#
#140
0#
#145
b0 !
b0 &
1#
