lab5/lab5/verilog/SPS_interface/bic.v
// bit identification count
// counts bits received and signals when frame has reached end
module bic(frameProgress, endFrame, enable, clk, rst);
	input	clk, rst,	// bit_clk
			enable;
	output endFrame;

	parameter FRAME_WIDTH = 10;

	output reg [3:0] frameProgress;
	initial frameProgress = 0;
	
	always@(posedge clk) begin
		if (rst) frameProgress <= 0;
		else begin
			if (enable) frameProgress <= frameProgress + 1'b1;
			else frameProgress <= 0;
		end
	end

	assign endFrame = (frameProgress == FRAME_WIDTH - 1);
endmodule

lab5/lab5/verilog/SPS_interface/bsc.v
// bit sample count
// counts samples (0-15) and outputs a posedge when hitting sample 7
module bsc(bitProgress, bit_clk, enable, clk, rst);
	input	clk, rst,	// 16xdata rate clk
			enable;
	output 	bit_clk;

	output reg [3:0] bitProgress;
	initial bitProgress = 0;
	
	always@(posedge clk) begin
		if (rst) bitProgress <= 0;
		else begin
			if (enable) bitProgress <= bitProgress + 1'b1;
			else bitProgress <= 0;
		end
	end

	assign bit_clk = (bitProgress == 7);
endmodule

lab5/lab5/verilog/SPS_interface/bitCounter.v
// bitCounter module
// counts samples and outputs a bit-clock and a signal for the end of the frame
module bitCounter(frameProgress, endFrame, bit_clk, enable, clk, rst);
	input	clk, rst,			// 16xdata rate clk
			enable;
	output bit_clk, endFrame;

	parameter FRAME_WIDTH = 10;

	output [3:0] frameProgress;

	bsc bitSample (.bit_clk(bit_clk), .enable(enable), .clk(clk), .rst(rst));
	bic #(FRAME_WIDTH) bitIdent (.frameProgress(frameProgress), .endFrame(endFrame), .enable(enable), .clk(bit_clk), .rst(rst));
endmodule

lab5/lab5/verilog/SPS_interface/bitCounter_testbench.v
module bitCounter_testbench();
	reg		clk, rst,
			enable;
	wire	endFrame, bit_clk;
	wire [3:0] frameProgress;

	// set up clock
	parameter PERIOD = 10;
	initial clk = 0;
	always begin
		#(PERIOD/2);
		clk = ~clk;
	end

	bitCounter #(11) dut (.frameProgress(frameProgress), .endFrame(endFrame), .bit_clk(bit_clk), .enable(enable), .clk(clk), .rst(rst));

	// begin simulation
	initial begin
		rst <= 1;					@(posedge clk);
		rst <= 0;	enable <= 0;	@(posedge clk);
					enable <= 1;	@(posedge clk); // bsc = 0, bic = 0
									@(posedge clk);
									@(posedge clk);
									@(posedge clk);
									@(posedge clk);
									@(posedge clk); // bsc = 5
									@(posedge clk);
									@(posedge clk); // bic = 1
									@(posedge clk);
									@(posedge clk);
									@(posedge clk); // bsc = 10
									@(posedge clk);
									@(posedge clk);
									@(posedge clk);
									@(posedge clk);
									@(posedge clk); // bsc = 15
									@(posedge clk); // bsc = 0
									@(posedge clk);
									@(posedge clk);
									@(posedge clk);
									@(posedge clk);
									@(posedge clk); // bsc = 5
									@(posedge clk);
									@(posedge clk); // bic = 2
									@(posedge clk);
									@(posedge clk);
									@(posedge clk); // bsc = 10
									@(posedge clk);
									@(posedge clk);
									@(posedge clk);
									@(posedge clk);
									@(posedge clk); // bsc = 15
									@(posedge clk); // bsc = 0
									@(posedge clk);
									@(posedge clk);
									@(posedge clk);
									@(posedge clk);
									@(posedge clk); // bsc = 5
									@(posedge clk);
									@(posedge clk); // bic = 3
									@(posedge clk);
									@(posedge clk);
									@(posedge clk); // bsc = 10
									@(posedge clk);
									@(posedge clk);
									@(posedge clk);
									@(posedge clk);
									@(posedge clk); // bsc = 15
									@(posedge clk); // bsc = 0
									@(posedge clk);
									@(posedge clk);
									@(posedge clk);
									@(posedge clk);
									@(posedge clk); // bsc = 5
									@(posedge clk);
									@(posedge clk); // bic = 4
									@(posedge clk);
									@(posedge clk);
									@(posedge clk); // bsc = 10
									@(posedge clk);
									@(posedge clk);
									@(posedge clk);
									@(posedge clk);
									@(posedge clk); // bsc = 15
									@(posedge clk); // bsc = 0
									@(posedge clk);
									@(posedge clk);
									@(posedge clk);
									@(posedge clk);
									@(posedge clk); // bsc = 5
									@(posedge clk);
									@(posedge clk); // bic = 5
									@(posedge clk);
									@(posedge clk);
									@(posedge clk); // bsc = 10
									@(posedge clk);
									@(posedge clk);
									@(posedge clk);
									@(posedge clk);
									@(posedge clk); // bsc = 15
									@(posedge clk); // bsc = 0
									@(posedge clk);
									@(posedge clk);
									@(posedge clk);
									@(posedge clk);
									@(posedge clk); // bsc = 5
									@(posedge clk);
									@(posedge clk); // bic = 6
									@(posedge clk);
									@(posedge clk);
									@(posedge clk); // bsc = 10
									@(posedge clk);
									@(posedge clk);
									@(posedge clk);
									@(posedge clk);
									@(posedge clk); // bsc = 15
									@(posedge clk); // bsc = 0
									@(posedge clk);
									@(posedge clk);
									@(posedge clk);
									@(posedge clk);
									@(posedge clk); // bsc = 5
									@(posedge clk);
									@(posedge clk); // bic = 7
									@(posedge clk);
									@(posedge clk);
									@(posedge clk); // bsc = 10
									@(posedge clk);
									@(posedge clk);
									@(posedge clk);
									@(posedge clk);
									@(posedge clk); // bsc = 15
									@(posedge clk); // bsc = 0
									@(posedge clk);
									@(posedge clk);
									@(posedge clk);
									@(posedge clk);
									@(posedge clk); // bsc = 5
									@(posedge clk);
									@(posedge clk); // bic = 8
									@(posedge clk);
									@(posedge clk);
									@(posedge clk); // bsc = 10
									@(posedge clk);
									@(posedge clk);
									@(posedge clk);
									@(posedge clk);
									@(posedge clk); // bsc = 15
									@(posedge clk); // bsc = 0
									@(posedge clk);
									@(posedge clk);
									@(posedge clk);
									@(posedge clk);
									@(posedge clk); // bsc = 5
									@(posedge clk);
									@(posedge clk); // bic = 9
									@(posedge clk);
									@(posedge clk);
									@(posedge clk); // bsc = 10
									@(posedge clk);
									@(posedge clk);
									@(posedge clk);
									@(posedge clk);
									@(posedge clk); // bsc = 15
									@(posedge clk); // bsc = 0
									@(posedge clk);
									@(posedge clk);
									@(posedge clk);
									@(posedge clk);
									@(posedge clk); // bsc = 5
									@(posedge clk);
									@(posedge clk); // bic = 10, 0 depending on param
									@(posedge clk);
									@(posedge clk);
									@(posedge clk); // bsc = 10
									@(posedge clk);
									@(posedge clk);
									@(posedge clk);
									@(posedge clk);
									@(posedge clk); // bsc = 15
									@(posedge clk); // bsc = 0
									@(posedge clk);
									@(posedge clk);
									@(posedge clk);
									@(posedge clk);
									@(posedge clk); // bsc = 5
									@(posedge clk);
									@(posedge clk); // bic = 0, 1 depending on param
									@(posedge clk);
									@(posedge clk);
									@(posedge clk); // bsc = 10
									@(posedge clk);
					enable <= 0;	@(posedge clk);
									@(posedge clk);
		$finish;
	end

	// gtkwave filedump
	initial begin
		$dumpfile("bitCounter.vcd");
		$dumpvars;
	end
endmodule

lab5/lab5/verilog/SPS_interface/bitCounter.vcd
$date
	Tue Dec  6 11:36:25 2016
$end
$version
	Icarus Verilog
$end
$timescale
	1s
$end
$scope module bitCounter_testbench $end
$var wire 4 ! frameProgress [3:0] $end
$var wire 1 " endFrame $end
$var wire 1 # bit_clk $end
$var reg 1 $ clk $end
$var reg 1 % enable $end
$var reg 1 & rst $end
$scope module dut $end
$var wire 1 $ clk $end
$var wire 1 % enable $end
$var wire 1 & rst $end
$var wire 4 ' frameProgress [3:0] $end
$var wire 1 " endFrame $end
$var wire 1 # bit_clk $end
$scope module bitIdent $end
$var wire 1 % enable $end
$var wire 1 & rst $end
$var wire 1 " endFrame $end
$var wire 1 # clk $end
$var reg 4 ( frameProgress [3:0] $end
$upscope $end
$scope module bitSample $end
$var wire 1 $ clk $end
$var wire 1 % enable $end
$var wire 1 & rst $end
$var wire 1 # bit_clk $end
$var reg 4 ) bitProgress [3:0] $end
$upscope $end
$upscope $end
$upscope $end
$enddefinitions $end
#0
$dumpvars
b0 )
b0 (
b0 '
1&
x%
0$
0#
0"
b0 !
$end
#5
0%
0&
1$
#10
0$
#15
1%
1$
#20
0$
#25
b1 )
1$
#30
0$
#35
b10 )
1$
#40
0$
#45
b11 )
1$
#50
0$
#55
b100 )
1$
#60
0$
#65
b101 )
1$
#70
0$
#75
b110 )
1$
#80
0$
#85
b1 !
b1 '
b1 (
1#
b111 )
1$
#90
0$
#95
0#
b1000 )
1$
#100
0$
#105
b1001 )
1$
#110
0$
#115
b1010 )
1$
#120
0$
#125
b1011 )
1$
#130
0$
#135
b1100 )
1$
#140
0$
#145
b1101 )
1$
#150
0$
#155
b1110 )
1$
#160
0$
#165
b1111 )
1$
#170
0$
#175
b0 )
1$
#180
0$
#185
b1 )
1$
#190
0$
#195
b10 )
1$
#200
0$
#205
b11 )
1$
#210
0$
#215
b100 )
1$
#220
0$
#225
b101 )
1$
#230
0$
#235
b110 )
1$
#240
0$
#245
b10 !
b10 '
b10 (
1#
b111 )
1$
#250
0$
#255
0#
b1000 )
1$
#260
0$
#265
b1001 )
1$
#270
0$
#275
b1010 )
1$
#280
0$
#285
b1011 )
1$
#290
0$
#295
b1100 )
1$
#300
0$
#305
b1101 )
1$
#310
0$
#315
b1110 )
1$
#320
0$
#325
b1111 )
1$
#330
0$
#335
b0 )
1$
#340
0$
#345
b1 )
1$
#350
0$
#355
b10 )
1$
#360
0$
#365
b11 )
1$
#370
0$
#375
b100 )
1$
#380
0$
#385
b101 )
1$
#390
0$
#395
b110 )
1$
#400
0$
#405
b11 !
b11 '
b11 (
1#
b111 )
1$
#410
0$
#415
0#
b1000 )
1$
#420
0$
#425
b1001 )
1$
#430
0$
#435
b1010 )
1$
#440
0$
#445
b1011 )
1$
#450
0$
#455
b1100 )
1$
#460
0$
#465
b1101 )
1$
#470
0$
#475
b1110 )
1$
#480
0$
#485
b1111 )
1$
#490
0$
#495
b0 )
1$
#500
0$
#505
b1 )
1$
#510
0$
#515
b10 )
1$
#520
0$
#525
b11 )
1$
#530
0$
#535
b100 )
1$
#540
0$
#545
b101 )
1$
#550
0$
#555
b110 )
1$
#560
0$
#565
b100 !
b100 '
b100 (
1#
b111 )
1$
#570
0$
#575
0#
b1000 )
1$
#580
0$
#585
b1001 )
1$
#590
0$
#595
b1010 )
1$
#600
0$
#605
b1011 )
1$
#610
0$
#615
b1100 )
1$
#620
0$
#625
b1101 )
1$
#630
0$
#635
b1110 )
1$
#640
0$
#645
b1111 )
1$
#650
0$
#655
b0 )
1$
#660
0$
#665
b1 )
1$
#670
0$
#675
b10 )
1$
#680
0$
#685
b11 )
1$
#690
0$
#695
b100 )
1$
#700
0$
#705
b101 )
1$
#710
0$
#715
b110 )
1$
#720
0$
#725
b101 !
b101 '
b101 (
1#
b111 )
1$
#730
0$
#735
0#
b1000 )
1$
#740
0$
#745
b1001 )
1$
#750
0$
#755
b1010 )
1$
#760
0$
#765
b1011 )
1$
#770
0$
#775
b1100 )
1$
#780
0$
#785
b1101 )
1$
#790
0$
#795
b1110 )
1$
#800
0$
#805
b1111 )
1$
#810
0$
#815
b0 )
1$
#820
0$
#825
b1 )
1$
#830
0$
#835
b10 )
1$
#840
0$
#845
b11 )
1$
#850
0$
#855
b100 )
1$
#860
0$
#865
b101 )
1$
#870
0$
#875
b110 )
1$
#880
0$
#885
b110 !
b110 '
b110 (
1#
b111 )
1$
#890
0$
#895
0#
b1000 )
1$
#900
0$
#905
b1001 )
1$
#910
0$
#915
b1010 )
1$
#920
0$
#925
b1011 )
1$
#930
0$
#935
b1100 )
1$
#940
0$
#945
b1101 )
1$
#950
0$
#955
b1110 )
1$
#960
0$
#965
b1111 )
1$
#970
0$
#975
b0 )
1$
#980
0$
#985
b1 )
1$
#990
0$
#995
b10 )
1$
#1000
0$
#1005
b11 )
1$
#1010
0$
#1015
b100 )
1$
#1020
0$
#1025
b101 )
1$
#1030
0$
#1035
b110 )
1$
#1040
0$
#1045
b111 !
b111 '
b111 (
1#
b111 )
1$
#1050
0$
#1055
0#
b1000 )
1$
#1060
0$
#1065
b1001 )
1$
#1070
0$
#1075
b1010 )
1$
#1080
0$
#1085
b1011 )
1$
#1090
0$
#1095
b1100 )
1$
#1100
0$
#1105
b1101 )
1$
#1110
0$
#1115
b1110 )
1$
#1120
0$
#1125
b1111 )
1$
#1130
0$
#1135
b0 )
1$
#1140
0$
#1145
b1 )
1$
#1150
0$
#1155
b10 )
1$
#1160
0$
#1165
b11 )
1$
#1170
0$
#1175
b100 )
1$
#1180
0$
#1185
b101 )
1$
#1190
0$
#1195
b110 )
1$
#1200
0$
#1205
b1000 !
b1000 '
b1000 (
1#
b111 )
1$
#1210
0$
#1215
0#
b1000 )
1$
#1220
0$
#1225
b1001 )
1$
#1230
0$
#1235
b1010 )
1$
#1240
0$
#1245
b1011 )
1$
#1250
0$
#1255
b1100 )
1$
#1260
0$
#1265
b1101 )
1$
#1270
0$
#1275
b1110 )
1$
#1280
0$
#1285
b1111 )
1$
#1290
0$
#1295
b0 )
1$
#1300
0$
#1305
b1 )
1$
#1310
0$
#1315
b10 )
1$
#1320
0$
#1325
b11 )
1$
#1330
0$
#1335
b100 )
1$
#1340
0$
#1345
b101 )
1$
#1350
0$
#1355
b110 )
1$
#1360
0$
#1365
b1001 !
b1001 '
b1001 (
1#
b111 )
1$
#1370
0$
#1375
0#
b1000 )
1$
#1380
0$
#1385
b1001 )
1$
#1390
0$
#1395
b1010 )
1$
#1400
0$
#1405
b1011 )
1$
#1410
0$
#1415
b1100 )
1$
#1420
0$
#1425
b1101 )
1$
#1430
0$
#1435
b1110 )
1$
#1440
0$
#1445
b1111 )
1$
#1450
0$
#1455
b0 )
1$
#1460
0$
#1465
b1 )
1$
#1470
0$
#1475
b10 )
1$
#1480
0$
#1485
b11 )
1$
#1490
0$
#1495
b100 )
1$
#1500
0$
#1505
b101 )
1$
#1510
0$
#1515
b110 )
1$
#1520
0$
#1525
1"
b1010 !
b1010 '
b1010 (
1#
b111 )
1$
#1530
0$
#1535
0#
b1000 )
1$
#1540
0$
#1545
b1001 )
1$
#1550
0$
#1555
b1010 )
1$
#1560
0$
#1565
b1011 )
1$
#1570
0$
#1575
b1100 )
1$
#1580
0$
#1585
b1101 )
1$
#1590
0$
#1595
b1110 )
1$
#1600
0$
#1605
b1111 )
1$
#1610
0$
#1615
b0 )
1$
#1620
0$
#1625
b1 )
1$
#1630
0$
#1635
b10 )
1$
#1640
0$
#1645
b11 )
1$
#1650
0$
#1655
b100 )
1$
#1660
0$
#1665
b101 )
1$
#1670
0$
#1675
b110 )
1$
#1680
0$
#1685
0"
b1011 !
b1011 '
b1011 (
1#
b111 )
1$
#1690
0$
#1695
0#
b1000 )
1$
#1700
0$
#1705
b1001 )
1$
#1710
0$
#1715
b1010 )
1$
#1720
0$
#1725
b1011 )
1$
#1730
0$
#1735
0%
b1100 )
1$
#1740
0$
#1745
b0 )
1$
