lab3/VHDL/counter.v
module counter(val, up, down, clk, reset);
	output [3:0] val;
	input up, down, clk, reset;

	// combinational logic to count every clock edge
	// min/max set at 0/10
	reg [3:0] ps, ns;
	always@(*) begin
		if (up && ~down && (ps < 4'b1010)) begin
			ns = ps + 1'b1;
		end else if (down && ~up && (ps > 4'b0000)) begin
			ns = ps - 1'b1;
		end else begin
			ns = ps;
		end
	end

	// output logic
	assign val = ps;
	
	// sequential logic; reset & next state
	always@(posedge clk) begin
		if (reset) begin
			ps <= 0;
		end else begin
			ps <= ns;
		end
	end
endmodule

lab3/VHDL/clock_divider.v
// EE371 Lab3 Autumn 2016
// authors: William Li, Dawn Liang, Jun Park
// date: 
// 
// clock divider module: outputs a 32-bit counter bus
//    choose the clock speed by choosing the bit
module clock_divider (divided_clocks, clk);
	input clk;
	output [31:0] divided_clocks;

	reg [31:0] clocks;
	initial clocks = 0;

	always@(posedge clk) begin
		clocks <= clocks + 1'b1;
	end

	assign divided_clocks = clocks;
endmodule

lab3/verilog/counterCtrl.v
// EE371 Lab 3 Autumn 2016
// Authors: Jun Park William Li Dawn Liang
// Date: 13 Nov 2016
//
// controls a counter that counts up/down at different speeds depending on
// the state input
`include "clock_divider.v"
`include "counter.v"
module counterCtrl(val, state, clk, reset);
	input [2:0] state;
	input clk, reset;

	output [3:0] val;

	// state encodings
	parameter	lowPower = 3'b000,
				standby = 3'b001,
				scanning = 3'b010,
				idle = 3'b011,
				xferring = 3'b100,
				flushing = 3'b101;

	// clock division
	wire [31:0] divided_clocks;
	clock_divider div (.divided_clocks(divided_clocks), .clk(clk));
	reg final_clock;

	// control signals
	reg up, down;
	always@(*) begin
		case (state)
			lowPower:	begin
							final_clock = divided_clocks[0];
							up = 0; down = 0;
						end
			standby:	begin
							final_clock = divided_clocks[0];
							up = 0; down = 0;
						end
			scanning:	begin 									// count up at 1x speed
							final_clock = divided_clocks[3];
							up = 1; down = 0;
						end
			idle:		begin
							final_clock = divided_clocks[0];
							up = 0; down = 0;
						end
			xferring:	begin 									// count down at 4x speed
							final_clock = divided_clocks[1];
							up = 0; down = 1;
						end
			flushing:	begin 									// count down at 8x speed
							final_clock = divided_clocks[0];
							up = 0; down = 1;
						end
			default:	begin
							final_clock = divided_clocks[0];
							up = 0; down = 0;
						end
		endcase
	end

	// counter
	counter prog (.val(val), .up(up), .down(down), .clk(final_clock), .reset(reset));
endmodule

lab3/verilog/counterCtrl_testbench.v
// EE371 Lab3 Autumn 2016
// Authors: Dawn Liang, Jun Park, William Li
// Date: 13 Nov 2016
//
// testbench for counterCtrl module; tests all possible state inputs
`include "counterCtrl.v"
module counterCtrl_testbench();
	reg [2:0] state;
	reg clk, reset;
	wire [3:0] val;

	counterCtrl dut (.val(val), .state(state), .clk(clk), .reset(reset));

	// set up clock
	parameter CLOCK_PERIOD = 10;
	initial clk = 0;
	always begin
		#(CLOCK_PERIOD/2);
		clk = ~clk;
	end

	initial begin
		reset <= 1;						@(posedge clk);
										@(posedge clk);
		reset <= 0;	state <= 3'b000;	@(posedge clk); // lowPower
										@(posedge clk);
										@(posedge clk);
					state <= 3'b001;	@(posedge clk); // standby
										@(posedge clk);
										@(posedge clk);
					state <= 3'b010;	@(posedge clk); // scanning
										@(posedge clk);
										@(posedge clk);
										@(posedge clk);
										@(posedge clk);
										@(posedge clk);
										@(posedge clk);
										@(posedge clk);
										@(posedge clk);
										@(posedge clk);
										@(posedge clk);
										@(posedge clk);
										@(posedge clk);
										@(posedge clk);
										@(posedge clk);
										@(posedge clk);
										@(posedge clk);
										@(posedge clk);
										@(posedge clk);
										@(posedge clk);
										@(posedge clk);
										@(posedge clk);
										@(posedge clk);
										@(posedge clk);
										@(posedge clk);
										@(posedge clk);
										@(posedge clk);
										@(posedge clk);
										@(posedge clk);
										@(posedge clk);
										@(posedge clk);
										@(posedge clk);
										@(posedge clk);
										@(posedge clk);
					state <= 3'b011;	@(posedge clk); // idle
										@(posedge clk);
										@(posedge clk);
										@(posedge clk);
										@(posedge clk);
										@(posedge clk);
										@(posedge clk);
										@(posedge clk);
										@(posedge clk);
										@(posedge clk);
										@(posedge clk);
										@(posedge clk);
										@(posedge clk);
										@(posedge clk);
										@(posedge clk);
					state <= 3'b100;	@(posedge clk); // xfer
										@(posedge clk);
										@(posedge clk);
										@(posedge clk);
										@(posedge clk);
										@(posedge clk);
					state <= 3'b101;	@(posedge clk); // flush
										@(posedge clk);
										@(posedge clk);
										@(posedge clk);
										@(posedge clk);
										@(posedge clk);
										@(posedge clk);
		$finish;
	end

	// gtkwave filedump
	initial begin
		$dumpfile("counterCtrl.vcd");
		$dumpvars;
	end
endmodule

lab3/verilog/counterCtrl.vcd
$date
	Wed Nov 23 20:22:59 2016
$end
$version
	Icarus Verilog
$end
$timescale
	1s
$end
$scope module counterCtrl_testbench $end
$var wire 4 ! val [3:0] $end
$var reg 1 " clk $end
$var reg 1 # reset $end
$var reg 3 $ state [2:0] $end
$scope module dut $end
$var wire 1 " clk $end
$var wire 1 # reset $end
$var wire 3 % state [2:0] $end
$var wire 4 & val [3:0] $end
$var wire 32 ' divided_clocks [31:0] $end
$var reg 1 ( down $end
$var reg 1 ) final_clock $end
$var reg 1 * up $end
$scope module div $end
$var wire 1 " clk $end
$var wire 32 + divided_clocks [31:0] $end
$var reg 32 , clocks [31:0] $end
$upscope $end
$scope module prog $end
$var wire 1 ) clk $end
$var wire 1 ( down $end
$var wire 1 # reset $end
$var wire 1 * up $end
$var wire 4 - val [3:0] $end
$var reg 4 . ns [3:0] $end
$var reg 4 / ps [3:0] $end
$upscope $end
$upscope $end
$upscope $end
$enddefinitions $end
#0
$dumpvars
bx /
bx .
bx -
b0 ,
b0 +
0*
0)
0(
b0 '
bx &
bx %
bx $
1#
0"
bx !
$end
#5
b0 .
b0 !
b0 &
b0 -
b0 /
1)
b1 '
b1 +
b1 ,
1"
#10
0"
#15
0)
b0 $
b0 %
0#
b10 '
b10 +
b10 ,
1"
#20
0"
#25
1)
b11 '
b11 +
b11 ,
1"
#30
0"
#35
0)
b100 '
b100 +
b100 ,
1"
#40
0"
#45
1)
b101 '
b101 +
b101 ,
b1 $
b1 %
1"
#50
0"
#55
0)
b110 '
b110 +
b110 ,
1"
#60
0"
#65
1)
b111 '
b111 +
b111 ,
1"
#70
0"
#75
b1 .
1*
b10 $
b10 %
b1000 '
b1000 +
b1000 ,
1"
#80
0"
#85
b1001 '
b1001 +
b1001 ,
1"
#90
0"
#95
b1010 '
b1010 +
b1010 ,
1"
#100
0"
#105
b1011 '
b1011 +
b1011 ,
1"
#110
0"
#115
b1100 '
b1100 +
b1100 ,
1"
#120
0"
#125
b1101 '
b1101 +
b1101 ,
1"
#130
0"
#135
b1110 '
b1110 +
b1110 ,
1"
#140
0"
#145
b1111 '
b1111 +
b1111 ,
1"
#150
0"
#155
0)
b10000 '
b10000 +
b10000 ,
1"
#160
0"
#165
b10001 '
b10001 +
b10001 ,
1"
#170
0"
#175
b10010 '
b10010 +
b10010 ,
1"
#180
0"
#185
b10011 '
b10011 +
b10011 ,
1"
#190
0"
#195
b10100 '
b10100 +
b10100 ,
1"
#200
0"
#205
b10101 '
b10101 +
b10101 ,
1"
#210
0"
#215
b10110 '
b10110 +
b10110 ,
1"
#220
0"
#225
b10111 '
b10111 +
b10111 ,
1"
#230
0"
#235
b10 .
b1 !
b1 &
b1 -
b1 /
1)
b11000 '
b11000 +
b11000 ,
1"
#240
0"
#245
b11001 '
b11001 +
b11001 ,
1"
#250
0"
#255
b11010 '
b11010 +
b11010 ,
1"
#260
0"
#265
b11011 '
b11011 +
b11011 ,
1"
#270
0"
#275
b11100 '
b11100 +
b11100 ,
1"
#280
0"
#285
b11101 '
b11101 +
b11101 ,
1"
#290
0"
#295
b11110 '
b11110 +
b11110 ,
1"
#300
0"
#305
b11111 '
b11111 +
b11111 ,
1"
#310
0"
#315
0)
b100000 '
b100000 +
b100000 ,
1"
#320
0"
#325
b100001 '
b100001 +
b100001 ,
1"
#330
0"
#335
b100010 '
b100010 +
b100010 ,
1"
#340
0"
#345
b100011 '
b100011 +
b100011 ,
1"
#350
0"
#355
b100100 '
b100100 +
b100100 ,
1"
#360
0"
#365
b100101 '
b100101 +
b100101 ,
1"
#370
0"
#375
b100110 '
b100110 +
b100110 ,
1"
#380
0"
#385
b100111 '
b100111 +
b100111 ,
1"
#390
0"
#395
b11 .
b10 !
b10 &
b10 -
b10 /
1)
b101000 '
b101000 +
b101000 ,
1"
#400
0"
#405
b101001 '
b101001 +
b101001 ,
1"
#410
0"
#415
b10 .
0*
0)
b11 $
b11 %
b101010 '
b101010 +
b101010 ,
1"
#420
0"
#425
1)
b101011 '
b101011 +
b101011 ,
1"
#430
0"
#435
0)
b101100 '
b101100 +
b101100 ,
1"
#440
0"
#445
1)
b101101 '
b101101 +
b101101 ,
1"
#450
0"
#455
0)
b101110 '
b101110 +
b101110 ,
1"
#460
0"
#465
1)
b101111 '
b101111 +
b101111 ,
1"
#470
0"
#475
0)
b110000 '
b110000 +
b110000 ,
1"
#480
0"
#485
1)
b110001 '
b110001 +
b110001 ,
1"
#490
0"
#495
0)
b110010 '
b110010 +
b110010 ,
1"
#500
0"
#505
1)
b110011 '
b110011 +
b110011 ,
1"
#510
0"
#515
0)
b110100 '
b110100 +
b110100 ,
1"
#520
0"
#525
1)
b110101 '
b110101 +
b110101 ,
1"
#530
0"
#535
0)
b110110 '
b110110 +
b110110 ,
1"
#540
0"
#545
1)
b110111 '
b110111 +
b110111 ,
1"
#550
0"
#555
0)
b111000 '
b111000 +
b111000 ,
1"
#560
0"
#565
b1 .
1(
b111001 '
b111001 +
b111001 ,
b100 $
b100 %
1"
#570
0"
#575
b0 .
b1 !
b1 &
b1 -
b1 /
1)
b111010 '
b111010 +
b111010 ,
1"
#580
0"
#585
b111011 '
b111011 +
b111011 ,
1"
#590
0"
#595
0)
b111100 '
b111100 +
b111100 ,
1"
#600
0"
#605
b111101 '
b111101 +
b111101 ,
1"
#610
0"
#615
b0 !
b0 &
b0 -
b0 /
1)
b111110 '
b111110 +
b111110 ,
1"
#620
0"
#625
b111111 '
b111111 +
b111111 ,
b101 $
b101 %
1"
#630
0"
#635
0)
b1000000 '
b1000000 +
b1000000 ,
1"
#640
0"
#645
1)
b1000001 '
b1000001 +
b1000001 ,
1"
#650
0"
#655
0)
b1000010 '
b1000010 +
b1000010 ,
1"
#660
0"
#665
1)
b1000011 '
b1000011 +
b1000011 ,
1"
#670
0"
#675
0)
b1000100 '
b1000100 +
b1000100 ,
1"
#680
0"
#685
1)
b1000101 '
b1000101 +
b1000101 ,
1"
#690
0"
#695
0)
b1000110 '
b1000110 +
b1000110 ,
1"
