lab5/verilog/scanner/counter.v
// EE371 Lab4 Autumn 2016
// Authors: Dawn Liang, Jun Park, William Li
// Date: 13 Nov 2016
//
// counter that counts every clock edge up/down to a min/max (0/10)
// resets to 0
module counter(data_out, data_in, percentage, up, down, clk, reset);
	output [3:0] percentage;
	input up, down, clk, reset;
	input [7:0] data_in;
	output [7:0] data_out;

	reg [7:0] mem [9:0]; // 10 x 8-bit memory

	// initialise the memory
	initial begin
		ps = 0;
		mem[0] = 8'b11111111;
		mem[1] = 8'b11111111;
		mem[2] = 8'b11111111;
		mem[3] = 8'b11111111;
		mem[4] = 8'b11111111;
		mem[5] = 8'b11111111;
		mem[6] = 8'b11111111;
		mem[7] = 8'b11111111;
		mem[8] = 8'b11111111;
		mem[9] = 8'b11111111;
	end

	// combinational logic: count every clock edge
	// min/max set at 0/10
	reg [3:0] ps, ns;
	always@(*) begin
		if (up && ~down && (ps < 10)) begin
			ns = ps + 1;
		end else if (down && ~up && (ps > 0)) begin
			ns = ps - 1;
		end else begin
			ns = ps;
		end
	end

	// output logic
	assign percentage = ps;
	assign data_out = mem[ps];
	
	// sequential logic; reset & next state
	always@(posedge clk) begin
		if (reset) begin 				// clear data
			ps <= 0;
			mem[0] <= 8'b11111111;
			mem[1] <= 8'b11111111;
			mem[2] <= 8'b11111111;
			mem[3] <= 8'b11111111;
			mem[4] <= 8'b11111111;
			mem[5] <= 8'b11111111;
			mem[6] <= 8'b11111111;
			mem[7] <= 8'b11111111;
			mem[8] <= 8'b11111111;
			mem[9] <= 8'b11111111;
		end else begin
			ps <= ns;
			if (down && ~up) begin 		// xfer/flushing; erase data
				mem[ps] <= 8'b11111111;
			end else if (ps < 9) begin 	// save new value
				mem[ps] <= data_in;
			end else begin 				// hold last value (full)
				mem[ps] <= mem[ps];
			end
		end
	end
endmodule

lab5/verilog/scanner/clock_divider.v
// EE371 Lab4 Autumn 2016
// authors: William Li, Dawn Liang, Jun Park
// date: 13 Nov 2016
// 
// clock divider module: outputs a 32-bit counter bus
//    choose the clock speed by choosing the bit
module clock_divider (divided_clocks, clk);
	input clk;
	output [31:0] divided_clocks;

	reg [31:0] clocks;
	initial clocks = 0;

	always@(posedge clk) begin
		clocks <= clocks + 1'b1;
	end

	assign divided_clocks = clocks;
endmodule

lab4/lab4/dataBuffer.v
// EE371 Lab 4 Autumn 2016
// Authors: Jun Park William Li Dawn Liang
// Date: 
//
// controls a counter that counts up/down at different speeds depending on
// the state input
module dataBuffer(data_out, data_in, percentage, state, clk, reset);
	input [2:0] state;
	input [7:0] data_in;
	input clk, reset;

	output [7:0] data_out;
	output [3:0] percentage;

	// state encodings
	parameter	lowPower = 3'b000,
				standby = 3'b001,
				scanning = 3'b010,
				idle = 3'b011,
				xferring = 3'b100,
				flushing = 3'b101;

	// clock division
	wire [31:0] divided_clocks;
	clock_divider div (.divided_clocks(divided_clocks), .clk(clk));
	reg final_clock;

	// control signals
	reg up, down;
	always@(*) begin
		case (state)
			lowPower:	begin
							final_clock = divided_clocks[0];
							up = 0; down = 0;
						end
			standby:	begin
							final_clock = divided_clocks[0];
							up = 0; down = 0;
						end
			scanning:	begin 									// count up at 1x speed
							final_clock = divided_clocks[3];
							up = 1; down = 0;
						end
			idle:		begin
							final_clock = divided_clocks[0];
							up = 0; down = 0;
						end
			xferring:	begin 									// count down at 4x speed
							final_clock = divided_clocks[1];
							up = 0; down = 1;
						end
			flushing:	begin 									// count down at 8x speed
							final_clock = divided_clocks[0];
							up = 0; down = 1;
						end
			default:	begin
							final_clock = divided_clocks[0];
							up = 0; down = 0;
						end
		endcase
	end

	// counter
	counter prog (.data_out(data_out), .data_in(data_in), .percentage(percentage), .up(up), .down(down), .clk(final_clock), .reset(reset));
endmodule

lab5/verilog/scanner/scannerState.v
// EE371 Lab3 Autumn 2016
// Authors: Dawn Liang, Jun Park, William Li
// Date: 13 Nov 2016
//
// FSM controlling the state of the scanner
module scannerState(state, whichScanner, initialOn, goToStandby, startScan, prog, startTransfer, flush, clk, reset);
	output [2:0] state;
	input whichScanner, initialOn, goToStandby, startScan, startTransfer, flush;
	input [3:0] prog;
	input clk, reset;

	// state encodings
	parameter	lowPower = 3'b000,
				standby = 3'b001,
				scanning = 3'b010,
				idle = 3'b011,
				xferring = 3'b100,
				flushing = 3'b101;

	// combinational logic: next state
	reg [2:0] ps, ns;
	initial ps  = lowPower;
	reg active;
	initial active = 0;
	always@(*) begin
		if (active) begin
			case (ps)
				lowPower:	begin
								if (goToStandby) ns = standby;
								else ns = ps;
							end
				standby:	begin
								if (startScan) ns = scanning;
								else ns = ps;
							end
				scanning:	begin
								if (prog == 4'b1010) ns = idle;
								else ns = ps;
							end
				idle:		begin
								if (startTransfer) ns = xferring;
								else if (flush) ns = flushing;
								else ns = ps;
							end
				xferring:	begin
								if (prog == 4'b0) ns = lowPower;
								else ns = ps;
							end
				flushing:	begin
								if (prog == 4'b0) ns = lowPower;
								else ns = ps;
							end
				default:	ns = ps;
			endcase
		end else begin
			if (initialOn) begin
				if (whichScanner) ns = scanning;
				else ns = lowPower;
			end else begin
				ns = lowPower;
			end
		end
	end

	// output logic
	assign state = ps;

	// sequential logic: reset, next state
	always@(posedge clk) begin
		if (reset) begin
			ps <= lowPower;
			active <= 0;
		end else begin
			ps <= ns;
			if (initialOn) active <= 1;
			else active <= active;
		end
	end
endmodule

lab4/lab4/scanner.v
// EE371 Lab4 Autumn 2016
// Authors: Dawn Liang, William Li, Jun Park
// Date: 
// 
// scanner module including FSM and counter for control and memory systems
// outputs current state & buffer progress, and control signals for other
// scanner
module scanner(data_out, buffer_progress, state, readyToTransfer, otherGoToStandby, otherStartScan, otherFlush,
				data_in, whichScanner, initialOn, goToStandby, startScan, startTransfer, flush, clk, reset);
	input clk, reset;
	input initialOn, goToStandby, startScan, startTransfer, flush, whichScanner;
	input [7:0] data_in;

	output readyToTransfer, otherGoToStandby, otherStartScan, otherFlush;
	output [3:0] buffer_progress;
	output [2:0] state;
	output [7:0] data_out;
	
	parameter scanning = 3'b010;

	scannerState ctrl (.state(state), .whichScanner(whichScanner), .initialOn(initialOn), .goToStandby(goToStandby), .startScan(startScan),
		.prog(buffer_progress), .startTransfer(startTransfer), .flush(flush), .clk(clk), .reset(reset));
	dataBuffer mem (.data_out(data_out), .data_in(data_in), .percentage(buffer_progress), .state(state), .clk(clk), .reset(reset));

	assign readyToTransfer = (buffer_progress == 5 && state == scanning);
	assign otherGoToStandby = (buffer_progress == 8 && state == scanning);
	assign otherStartScan = (buffer_progress == 9 && state == scanning);
	assign otherFlush = (buffer_progress == 5 && state == scanning);
endmodule

lab5/lab5/verilog/scanner/scannerIO.v
// scannerIO
module scannerIO(s1_data_out, s2_data_out, s1_state, s2_state, data_out, data_in, readyToTransfer, startScanning, transfer, clk, rst);
	input			clk, rst,					// 50MHz clk
					startScanning, transfer;
	input [7:0]		data_in;
	output [7:0]	data_out;
	output 			readyToTransfer;
	output [2:0]	s1_state, s2_state;

	// state encodings
	parameter LOWPOWER = 3'b000;
	parameter STANDBY = 3'b001;
	parameter SCANNING = 3'b010;
	parameter IDLE = 3'b011;
	parameter TRANSFER = 3'b100;
	parameter FLUSHING = 3'b101;

	// clock divider
	// wire [31:0] divided_clocks;
	// clock_divider cdiv (.divided_clocks(divided_clocks), .clk(clk));
	// assign final_clock = divided_clocks[22];

	// scanner subsystem
	output [7:0]	s1_data_out, s2_data_out;
	wire [3:0]	s1_buffer_progress, s2_buffer_progress;
	wire		s1_readyToTransfer, s2_readyToTransfer,
				s1_otherGoToStandby, s2_otherGoToStandby,
				s1_otherStartScan, s2_otherStartScan,
				s1_otherFlush, s2_otherFlush;

	scanner s1 (.data_out(s1_data_out), .buffer_progress(s1_buffer_progress), .state(s1_state), .readyToTransfer(s1_readyToTransfer), .otherGoToStandby(s1_otherGoToStandby), .otherStartScan(s1_otherStartScan), .otherFlush(s1_otherFlush),
				.data_in(data_in), .whichScanner(1'b1), .initialOn(startScanning), .goToStandby(s2_otherGoToStandby), .startScan(s2_otherStartScan), .startTransfer(transfer), .flush(s2_otherFlush), .clk(clk), .reset(rst));
	scanner s2 (.data_out(s2_data_out), .buffer_progress(s2_buffer_progress), .state(s2_state), .readyToTransfer(s2_readyToTransfer), .otherGoToStandby(s2_otherGoToStandby), .otherStartScan(s2_otherStartScan), .otherFlush(s2_otherFlush),
				.data_in(data_in), .whichScanner(1'b0), .initialOn(startScanning), .goToStandby(s1_otherGoToStandby), .startScan(s1_otherStartScan), .startTransfer(transfer), .flush(s1_otherFlush), .clk(clk), .reset(rst));

	// if either scanner is ready to transfer
	assign readyToTransfer = (s1_readyToTransfer || s2_readyToTransfer);

	// output the data of the transferring scanner
	reg [7:0] data_tgl;
	initial data_tgl = 8'b11111111;
	always@(*) begin
		if (s1_state == TRANSFER) data_tgl = s1_data_out;
		else if (s2_state == TRANSFER) data_tgl = s2_data_out;
		else data_tgl = 8'b11111111;
	end
	assign data_out = data_tgl;
endmodule

lab5/lab5/verilog/scanner/scannerIO_testbench.v
module scannerIO_testbench();
	reg			clk, rst,
				startScanning, transfer;
	reg [7:0]	data_in;
	wire 		readyToTransfer;
	wire [7:0]	data_out, s1_data_out, s2_data_out;
	wire [2:0]	s1_state, s2_state;

	// set up clock
	parameter PERIOD = 10;
	initial clk = 0;
	always begin
		#(PERIOD/2);
		clk = ~clk;
	end

	scannerIO dut (.s1_data_out(s1_data_out), .s2_data_out(s2_data_out), .s1_state(s1_state), .s2_state(s2_state), .data_out(data_out), .data_in(data_in), .readyToTransfer(readyToTransfer), .startScanning(startScanning), .transfer(transfer), .clk(clk), .rst(rst));

	// begin simulation
	initial begin
		rst <= 1;	data_in <= 8'b10101010;				@(posedge clk);
														@(posedge clk);
		rst <= 0;	startScanning <= 0;	transfer <= 0;	@(posedge clk);
					startScanning <= 1;					@(posedge clk);
														@(posedge clk);
					startScanning <= 0;					@(posedge clk);
														@(posedge clk);
														@(posedge clk);
														@(posedge clk);
														@(posedge clk);
														@(posedge clk);
														@(posedge clk);
														@(posedge clk);
														@(posedge clk);
														@(posedge clk);
														@(posedge clk);
														@(posedge clk);
														@(posedge clk);
														@(posedge clk);
														@(posedge clk);
														@(posedge clk);
														@(posedge clk);
														@(posedge clk);
														@(posedge clk);
														@(posedge clk);
														@(posedge clk);
														@(posedge clk);
														@(posedge clk);
														@(posedge clk);
														@(posedge clk);
														@(posedge clk);
														@(posedge clk);
														@(posedge clk);
														@(posedge clk);
														@(posedge clk);
														@(posedge clk);
														@(posedge clk);
														@(posedge clk);
														@(posedge clk);
														@(posedge clk);
														@(posedge clk);
														@(posedge clk);
														@(posedge clk);
														@(posedge clk);
														@(posedge clk);
														@(posedge clk);
														@(posedge clk);
														@(posedge clk);
														@(posedge clk);
														@(posedge clk);
														@(posedge clk);
														@(posedge clk);
														@(posedge clk);
														@(posedge clk);
														@(posedge clk);
														@(posedge clk);
														@(posedge clk);
														@(posedge clk);
														@(posedge clk);
														@(posedge clk);
														@(posedge clk);
														@(posedge clk);
														@(posedge clk);
														@(posedge clk);
														@(posedge clk);
														@(posedge clk);
														@(posedge clk);
														@(posedge clk);
														@(posedge clk);
														@(posedge clk);
														@(posedge clk);
														@(posedge clk);
														@(posedge clk);
														@(posedge clk);
														@(posedge clk);
														@(posedge clk);
														@(posedge clk);
														@(posedge clk);
														@(posedge clk);
														@(posedge clk);
														@(posedge clk);
														@(posedge clk);
														@(posedge clk);
														@(posedge clk);
														@(posedge clk);
														@(posedge clk);
														@(posedge clk);
														@(posedge clk);
														@(posedge clk);
														@(posedge clk);
														@(posedge clk);
														@(posedge clk);
														@(posedge clk);
														@(posedge clk);
														@(posedge clk);
														@(posedge clk);
														@(posedge clk);
														@(posedge clk);
														@(posedge clk);
														@(posedge clk);
														@(posedge clk);
														@(posedge clk);
														@(posedge clk);
														@(posedge clk);
														@(posedge clk);
														@(posedge clk);
														@(posedge clk);
														@(posedge clk);
														@(posedge clk);
														@(posedge clk);
														@(posedge clk);
														@(posedge clk);
														@(posedge clk);
														@(posedge clk);
														@(posedge clk);
														@(posedge clk);
														@(posedge clk);
														@(posedge clk);
														@(posedge clk);
														@(posedge clk);
														@(posedge clk);
														@(posedge clk);
														@(posedge clk);
														@(posedge clk);
														@(posedge clk);
														@(posedge clk);
														@(posedge clk);
														@(posedge clk);
														@(posedge clk);
														@(posedge clk);
														@(posedge clk);
														@(posedge clk);
														@(posedge clk);
														@(posedge clk);
														@(posedge clk);
														@(posedge clk);
														@(posedge clk);
														@(posedge clk);
														@(posedge clk);
														@(posedge clk);
														@(posedge clk);
														@(posedge clk);
														@(posedge clk);
														@(posedge clk);
														@(posedge clk);
														@(posedge clk);
														@(posedge clk);
														@(posedge clk);
														@(posedge clk);
														@(posedge clk);
														@(posedge clk);
														@(posedge clk);
														@(posedge clk);
														@(posedge clk);
														@(posedge clk);
														@(posedge clk);
														@(posedge clk);
														@(posedge clk);
														@(posedge clk);
														@(posedge clk);
														@(posedge clk);
														@(posedge clk);
														@(posedge clk);
														@(posedge clk);
														@(posedge clk);
														@(posedge clk);
														@(posedge clk);
														@(posedge clk);
														@(posedge clk);
														@(posedge clk);
														@(posedge clk);
														@(posedge clk);
														@(posedge clk);
														@(posedge clk);
														@(posedge clk);
														@(posedge clk);
														@(posedge clk);
														@(posedge clk);
														@(posedge clk);
										transfer <= 1;	@(posedge clk);
										transfer <= 0;	@(posedge clk);
														@(posedge clk);
														@(posedge clk);
														@(posedge clk);
														@(posedge clk);
														@(posedge clk);
														@(posedge clk);
														@(posedge clk);
														@(posedge clk);
														@(posedge clk);
														@(posedge clk);
														@(posedge clk);
														@(posedge clk);
														@(posedge clk);
														@(posedge clk);
														@(posedge clk);
														@(posedge clk);
														@(posedge clk);
														@(posedge clk);
														@(posedge clk);
														@(posedge clk);
														@(posedge clk);
														@(posedge clk);
														@(posedge clk);
														@(posedge clk);
														@(posedge clk);
														@(posedge clk);
														@(posedge clk);
														@(posedge clk);
														@(posedge clk);
														@(posedge clk);
														@(posedge clk);
														@(posedge clk);
														@(posedge clk);
														@(posedge clk);
														@(posedge clk);
														@(posedge clk);
														@(posedge clk);
														@(posedge clk);
														@(posedge clk);
														@(posedge clk);
														@(posedge clk);
														@(posedge clk);
														@(posedge clk);
														@(posedge clk);
														@(posedge clk);
														@(posedge clk);
														@(posedge clk);
														@(posedge clk);
														@(posedge clk);
														@(posedge clk);
														@(posedge clk);
														@(posedge clk);
														@(posedge clk);
														@(posedge clk);
														@(posedge clk);
														@(posedge clk);
														@(posedge clk);
														@(posedge clk);
														@(posedge clk);
														@(posedge clk);
														@(posedge clk);
														@(posedge clk);
														@(posedge clk);
														@(posedge clk);
														@(posedge clk);
														@(posedge clk);
														@(posedge clk);
														@(posedge clk);
														@(posedge clk);
														@(posedge clk);
														@(posedge clk);
														@(posedge clk);
														@(posedge clk);
														@(posedge clk);
														@(posedge clk);
														@(posedge clk);
														@(posedge clk);
														@(posedge clk);
														@(posedge clk);
														@(posedge clk);
														@(posedge clk);
														@(posedge clk);
														@(posedge clk);
														@(posedge clk);
														@(posedge clk);
														@(posedge clk);
														@(posedge clk);
														@(posedge clk);
														@(posedge clk);
														@(posedge clk);
														@(posedge clk);
														@(posedge clk);
														@(posedge clk);
														@(posedge clk);
														@(posedge clk);
														@(posedge clk);
														@(posedge clk);
														@(posedge clk);
														@(posedge clk);
														@(posedge clk);
														@(posedge clk);
														@(posedge clk);
														@(posedge clk);
														@(posedge clk);
														@(posedge clk);
														@(posedge clk);
														@(posedge clk);
														@(posedge clk);
														@(posedge clk);
														@(posedge clk);
														@(posedge clk);
														@(posedge clk);
														@(posedge clk);
														@(posedge clk);
														@(posedge clk);
														@(posedge clk);
														@(posedge clk);
														@(posedge clk);
														@(posedge clk);
														@(posedge clk);
														@(posedge clk);
														@(posedge clk);
														@(posedge clk);
														@(posedge clk);
														@(posedge clk);
														@(posedge clk);
														@(posedge clk);
														@(posedge clk);
														@(posedge clk);
														@(posedge clk);
														@(posedge clk);
														@(posedge clk);
														@(posedge clk);
														@(posedge clk);
														@(posedge clk);
														@(posedge clk);
														@(posedge clk);
														@(posedge clk);
														@(posedge clk);
														@(posedge clk);
														@(posedge clk);
														@(posedge clk);
														@(posedge clk);
														@(posedge clk);
														@(posedge clk);
														@(posedge clk);
														@(posedge clk);
														@(posedge clk);
														@(posedge clk);
														@(posedge clk);
														@(posedge clk);
														@(posedge clk);
										transfer <= 1;	@(posedge clk);
										transfer <= 0;	@(posedge clk);
														@(posedge clk);
														@(posedge clk);
														@(posedge clk);
														@(posedge clk);
														@(posedge clk);
														@(posedge clk);
														@(posedge clk);
														@(posedge clk);
														@(posedge clk);
														@(posedge clk);
														@(posedge clk);
														@(posedge clk);
														@(posedge clk);
														@(posedge clk);
														@(posedge clk);
														@(posedge clk);
														@(posedge clk);
														@(posedge clk);
														@(posedge clk);
														@(posedge clk);
														@(posedge clk);
														@(posedge clk);
														@(posedge clk);
														@(posedge clk);
														@(posedge clk);
														@(posedge clk);
														@(posedge clk);
														@(posedge clk);
														@(posedge clk);
														@(posedge clk);
														@(posedge clk);
														@(posedge clk);
														@(posedge clk);
														@(posedge clk);
														@(posedge clk);
														@(posedge clk);
														@(posedge clk);
														@(posedge clk);
														@(posedge clk);
		$finish;
	end

	// gtkwave filedump
	initial begin
		$dumpfile("scannerIO.vcd");
		$dumpvars;
	end
endmodule

lab5/verilog/scanner/scannerIO.vcd
$date
	Tue Dec  6 16:00:45 2016
$end
$version
	Icarus Verilog
$end
$timescale
	1s
$end
$scope module scannerIO_testbench $end
$var wire 3 ! s2_state [2:0] $end
$var wire 8 " s2_data_out [7:0] $end
$var wire 3 # s1_state [2:0] $end
$var wire 8 $ s1_data_out [7:0] $end
$var wire 1 % readyToTransfer $end
$var wire 8 & data_out [7:0] $end
$var reg 1 ' clk $end
$var reg 8 ( data_in [7:0] $end
$var reg 1 ) rst $end
$var reg 1 * startScanning $end
$var reg 1 + transfer $end
$scope module dut $end
$var wire 1 ' clk $end
$var wire 8 , data_in [7:0] $end
$var wire 8 - data_out [7:0] $end
$var wire 1 % readyToTransfer $end
$var wire 1 ) rst $end
$var wire 1 * startScanning $end
$var wire 1 + transfer $end
$var wire 3 . s2_state [2:0] $end
$var wire 1 / s2_readyToTransfer $end
$var wire 1 0 s2_otherStartScan $end
$var wire 1 1 s2_otherGoToStandby $end
$var wire 1 2 s2_otherFlush $end
$var wire 8 3 s2_data_out [7:0] $end
$var wire 4 4 s2_buffer_progress [3:0] $end
$var wire 3 5 s1_state [2:0] $end
$var wire 1 6 s1_readyToTransfer $end
$var wire 1 7 s1_otherStartScan $end
$var wire 1 8 s1_otherGoToStandby $end
$var wire 1 9 s1_otherFlush $end
$var wire 8 : s1_data_out [7:0] $end
$var wire 4 ; s1_buffer_progress [3:0] $end
$var reg 8 < data_tgl [7:0] $end
$scope module s1 $end
$var wire 1 ' clk $end
$var wire 8 = data_in [7:0] $end
$var wire 1 * initialOn $end
$var wire 1 9 otherFlush $end
$var wire 1 8 otherGoToStandby $end
$var wire 1 7 otherStartScan $end
$var wire 1 6 readyToTransfer $end
$var wire 1 ) reset $end
$var wire 1 + startTransfer $end
$var wire 1 > whichScanner $end
$var wire 3 ? state [2:0] $end
$var wire 1 0 startScan $end
$var wire 1 1 goToStandby $end
$var wire 1 2 flush $end
$var wire 8 @ data_out [7:0] $end
$var wire 4 A buffer_progress [3:0] $end
$scope module ctrl $end
$var wire 1 ' clk $end
$var wire 1 * initialOn $end
$var wire 1 ) reset $end
$var wire 1 + startTransfer $end
$var wire 3 B state [2:0] $end
$var wire 1 > whichScanner $end
$var wire 1 0 startScan $end
$var wire 4 C prog [3:0] $end
$var wire 1 1 goToStandby $end
$var wire 1 2 flush $end
$var reg 1 D active $end
$var reg 3 E ns [2:0] $end
$var reg 3 F ps [2:0] $end
$upscope $end
$scope module mem $end
$var wire 1 ' clk $end
$var wire 8 G data_in [7:0] $end
$var wire 1 ) reset $end
$var wire 3 H state [2:0] $end
$var wire 4 I percentage [3:0] $end
$var wire 32 J divided_clocks [31:0] $end
$var wire 8 K data_out [7:0] $end
$var reg 1 L down $end
$var reg 1 M final_clock $end
$var reg 1 N up $end
$scope module div $end
$var wire 1 ' clk $end
$var wire 32 O divided_clocks [31:0] $end
$var reg 32 P clocks [31:0] $end
$upscope $end
$scope module prog $end
$var wire 1 M clk $end
$var wire 8 Q data_in [7:0] $end
$var wire 8 R data_out [7:0] $end
$var wire 1 L down $end
$var wire 4 S percentage [3:0] $end
$var wire 1 ) reset $end
$var wire 1 N up $end
$var reg 4 T ns [3:0] $end
$var reg 4 U ps [3:0] $end
$upscope $end
$upscope $end
$upscope $end
$scope module s2 $end
$var wire 1 ' clk $end
$var wire 8 V data_in [7:0] $end
$var wire 1 9 flush $end
$var wire 1 8 goToStandby $end
$var wire 1 * initialOn $end
$var wire 1 2 otherFlush $end
$var wire 1 1 otherGoToStandby $end
$var wire 1 0 otherStartScan $end
$var wire 1 / readyToTransfer $end
$var wire 1 ) reset $end
$var wire 1 7 startScan $end
$var wire 1 + startTransfer $end
$var wire 1 W whichScanner $end
$var wire 3 X state [2:0] $end
$var wire 8 Y data_out [7:0] $end
$var wire 4 Z buffer_progress [3:0] $end
$scope module ctrl $end
$var wire 1 ' clk $end
$var wire 1 9 flush $end
$var wire 1 8 goToStandby $end
$var wire 1 * initialOn $end
$var wire 1 ) reset $end
$var wire 1 7 startScan $end
$var wire 1 + startTransfer $end
$var wire 3 [ state [2:0] $end
$var wire 1 W whichScanner $end
$var wire 4 \ prog [3:0] $end
$var reg 1 ] active $end
$var reg 3 ^ ns [2:0] $end
$var reg 3 _ ps [2:0] $end
$upscope $end
$scope module mem $end
$var wire 1 ' clk $end
$var wire 8 ` data_in [7:0] $end
$var wire 1 ) reset $end
$var wire 3 a state [2:0] $end
$var wire 4 b percentage [3:0] $end
$var wire 32 c divided_clocks [31:0] $end
$var wire 8 d data_out [7:0] $end
$var reg 1 e down $end
$var reg 1 f final_clock $end
$var reg 1 g up $end
$scope module div $end
$var wire 1 ' clk $end
$var wire 32 h divided_clocks [31:0] $end
$var reg 32 i clocks [31:0] $end
$upscope $end
$scope module prog $end
$var wire 1 f clk $end
$var wire 8 j data_in [7:0] $end
$var wire 8 k data_out [7:0] $end
$var wire 1 e down $end
$var wire 4 l percentage [3:0] $end
$var wire 1 ) reset $end
$var wire 1 g up $end
$var reg 4 m ns [3:0] $end
$var reg 4 n ps [3:0] $end
$upscope $end
$upscope $end
$upscope $end
$upscope $end
$upscope $end
$enddefinitions $end
#0
$dumpvars
b0 n
b0 m
b0 l
b11111111 k
b10101010 j
b0 i
b0 h
0g
0f
0e
b11111111 d
b0 c
b0 b
b0 a
b10101010 `
b0 _
b0 ^
0]
b0 \
b0 [
b0 Z
b11111111 Y
b0 X
0W
b10101010 V
b0 U
b0 T
b0 S
b11111111 R
b10101010 Q
b0 P
b0 O
0N
0M
0L
b11111111 K
b0 J
b0 I
b0 H
b10101010 G
b0 F
b0 E
0D
b0 C
b0 B
b0 A
b11111111 @
b0 ?
1>
b10101010 =
b11111111 <
b0 ;
b11111111 :
09
08
07
06
b0 5
b0 4
b11111111 3
02
01
00
0/
b0 .
b11111111 -
b10101010 ,
x+
x*
1)
b10101010 (
0'
b11111111 &
0%
b11111111 $
b0 #
b11111111 "
b0 !
$end
#5
1M
1f
b1 J
b1 O
b1 P
b1 c
b1 h
b1 i
1'
#10
0'
#15
0f
0M
0+
0*
0)
b10 c
b10 h
b10 i
b10 J
b10 O
b10 P
1'
#20
0'
#25
b10101010 $
b10101010 :
b10101010 @
b10101010 K
b10101010 R
b10101010 "
b10101010 3
b10101010 Y
b10101010 d
b10101010 k
1M
1f
b10 E
b11 J
b11 O
b11 P
b11 c
b11 h
b11 i
1*
1'
#30
0'
#35
b1 T
0f
1N
0M
b100 c
b100 h
b100 i
1]
b100 J
b100 O
b100 P
1D
b10 #
b10 5
b10 ?
b10 B
b10 F
b10 H
1'
#40
0'
#45
1f
b101 J
b101 O
b101 P
b101 c
b101 h
b101 i
0*
1'
#50
0'
#55
0f
b110 c
b110 h
b110 i
b110 J
b110 O
b110 P
1'
#60
0'
#65
1f
b111 J
b111 O
b111 P
b111 c
b111 h
b111 i
1'
#70
0'
#75
b10 T
b11111111 $
b11111111 :
b11111111 @
b11111111 K
b11111111 R
b1 ;
b1 A
b1 C
b1 I
b1 S
b1 U
0f
1M
b1000 c
b1000 h
b1000 i
b1000 J
b1000 O
b1000 P
1'
#80
0'
#85
1f
b1001 J
b1001 O
b1001 P
b1001 c
b1001 h
b1001 i
1'
#90
0'
#95
0f
b1010 c
b1010 h
b1010 i
b1010 J
b1010 O
b1010 P
1'
#100
0'
#105
1f
b1011 J
b1011 O
b1011 P
b1011 c
b1011 h
b1011 i
1'
#110
0'
#115
0f
b1100 c
b1100 h
b1100 i
b1100 J
b1100 O
b1100 P
1'
#120
0'
#125
1f
b1101 J
b1101 O
b1101 P
b1101 c
b1101 h
b1101 i
1'
#130
0'
#135
0f
b1110 c
b1110 h
b1110 i
b1110 J
b1110 O
b1110 P
1'
#140
0'
#145
1f
b1111 J
b1111 O
b1111 P
b1111 c
b1111 h
b1111 i
1'
#150
0'
#155
0f
0M
b10000 c
b10000 h
b10000 i
b10000 J
b10000 O
b10000 P
1'
#160
0'
#165
1f
b10001 J
b10001 O
b10001 P
b10001 c
b10001 h
b10001 i
1'
#170
0'
#175
0f
b10010 c
b10010 h
b10010 i
b10010 J
b10010 O
b10010 P
1'
#180
0'
#185
1f
b10011 J
b10011 O
b10011 P
b10011 c
b10011 h
b10011 i
1'
#190
0'
#195
0f
b10100 c
b10100 h
b10100 i
b10100 J
b10100 O
b10100 P
1'
#200
0'
#205
1f
b10101 J
b10101 O
b10101 P
b10101 c
b10101 h
b10101 i
1'
#210
0'
#215
0f
b10110 c
b10110 h
b10110 i
b10110 J
b10110 O
b10110 P
1'
#220
0'
#225
1f
b10111 J
b10111 O
b10111 P
b10111 c
b10111 h
b10111 i
1'
#230
0'
#235
b11 T
b10 ;
b10 A
b10 C
b10 I
b10 S
b10 U
0f
1M
b11000 c
b11000 h
b11000 i
b11000 J
b11000 O
b11000 P
1'
#240
0'
#245
1f
b11001 J
b11001 O
b11001 P
b11001 c
b11001 h
b11001 i
1'
#250
0'
#255
0f
b11010 c
b11010 h
b11010 i
b11010 J
b11010 O
b11010 P
1'
#260
0'
#265
1f
b11011 J
b11011 O
b11011 P
b11011 c
b11011 h
b11011 i
1'
#270
0'
#275
0f
b11100 c
b11100 h
b11100 i
b11100 J
b11100 O
b11100 P
1'
#280
0'
#285
1f
b11101 J
b11101 O
b11101 P
b11101 c
b11101 h
b11101 i
1'
#290
0'
#295
0f
b11110 c
b11110 h
b11110 i
b11110 J
b11110 O
b11110 P
1'
#300
0'
#305
1f
b11111 J
b11111 O
b11111 P
b11111 c
b11111 h
b11111 i
1'
#310
0'
#315
0f
0M
b100000 c
b100000 h
b100000 i
b100000 J
b100000 O
b100000 P
1'
#320
0'
#325
1f
b100001 J
b100001 O
b100001 P
b100001 c
b100001 h
b100001 i
1'
#330
0'
#335
0f
b100010 c
b100010 h
b100010 i
b100010 J
b100010 O
b100010 P
1'
#340
0'
#345
1f
b100011 J
b100011 O
b100011 P
b100011 c
b100011 h
b100011 i
1'
#350
0'
#355
0f
b100100 c
b100100 h
b100100 i
b100100 J
b100100 O
b100100 P
1'
#360
0'
#365
1f
b100101 J
b100101 O
b100101 P
b100101 c
b100101 h
b100101 i
1'
#370
0'
#375
0f
b100110 c
b100110 h
b100110 i
b100110 J
b100110 O
b100110 P
1'
#380
0'
#385
1f
b100111 J
b100111 O
b100111 P
b100111 c
b100111 h
b100111 i
1'
#390
0'
#395
b100 T
b11 ;
b11 A
b11 C
b11 I
b11 S
b11 U
0f
1M
b101000 c
b101000 h
b101000 i
b101000 J
b101000 O
b101000 P
1'
#400
0'
#405
1f
b101001 J
b101001 O
b101001 P
b101001 c
b101001 h
b101001 i
1'
#410
0'
#415
0f
b101010 c
b101010 h
b101010 i
b101010 J
b101010 O
b101010 P
1'
#420
0'
#425
1f
b101011 J
b101011 O
b101011 P
b101011 c
b101011 h
b101011 i
1'
#430
0'
#435
0f
b101100 c
b101100 h
b101100 i
b101100 J
b101100 O
b101100 P
1'
#440
0'
#445
1f
b101101 J
b101101 O
b101101 P
b101101 c
b101101 h
b101101 i
1'
#450
0'
#455
0f
b101110 c
b101110 h
b101110 i
b101110 J
b101110 O
b101110 P
1'
#460
0'
#465
1f
b101111 J
b101111 O
b101111 P
b101111 c
b101111 h
b101111 i
1'
#470
0'
#475
0f
0M
b110000 c
b110000 h
b110000 i
b110000 J
b110000 O
b110000 P
1'
#480
0'
#485
1f
b110001 J
b110001 O
b110001 P
b110001 c
b110001 h
b110001 i
1'
#490
0'
#495
0f
b110010 c
b110010 h
b110010 i
b110010 J
b110010 O
b110010 P
1'
#500
0'
#505
1f
b110011 J
b110011 O
b110011 P
b110011 c
b110011 h
b110011 i
1'
#510
0'
#515
0f
b110100 c
b110100 h
b110100 i
b110100 J
b110100 O
b110100 P
1'
#520
0'
#525
1f
b110101 J
b110101 O
b110101 P
b110101 c
b110101 h
b110101 i
1'
#530
0'
#535
0f
b110110 c
b110110 h
b110110 i
b110110 J
b110110 O
b110110 P
1'
#540
0'
#545
1f
b110111 J
b110111 O
b110111 P
b110111 c
b110111 h
b110111 i
1'
#550
0'
#555
b101 T
b100 ;
b100 A
b100 C
b100 I
b100 S
b100 U
0f
1M
b111000 c
b111000 h
b111000 i
b111000 J
b111000 O
b111000 P
1'
#560
0'
