lab2.1/upDownCounter.v
module upDownCounter(out, up, down, diffOkArriv, diffOkDept, clk, reset);
	output [3:0] out;
	input up, down, clk, reset, diffOkArriv, diffOkDept;
	
	reg [3:0] val;
	reg enable;
	wire start, stop;

	assign start = up || down;
	assign stop = diffOkDept || diffOkArriv;

	assign out = val;

	always @(posedge clk) begin
		if (reset) begin
			val <= 4'b0000;
			enable <= 0;
		end else begin
			case(enable)
				0:	if (start) begin
						enable <= 1;
						if(up && ~down && (val < 4'b1111)) begin 			// count up
							val <= val + 1'b1;
						end else if (down && ~up && (val > 4'b0000)) begin // count down
							val <= val - 1'b1;
						end else begin 										// don't count
							val <= val;
						end
					end else begin
						val <= val;
					end
				1:	if (stop) begin
						enable <= 0;
						val <= val;
					end else begin
						if(up && ~down && (val < 4'b1111)) begin 			// count up
							val <= val + 1'b1;
						end else if (down && ~up && (val > 4'b0000)) begin // count down
							val <= val - 1'b1;
						end else begin 										// don't count
							val <= val;
						end
					end
			endcase
		end
	end
endmodule

lab2.1/adjustWater.v
`include "upDownCounter.v"
module adjustWater(insideLvl, incr, decr, arrOutsideLvl, deptOutsideLvl, diffOkArr, diffOkDept, clk, reset);
	input clk, reset;
	input incr, decr;
	input [3:0] arrOutsideLvl, deptOutsideLvl;

	output diffOkArr, diffOkDept;

	output [3:0] insideLvl;

	upDownCounter counter (.out(insideLvl), .up(incr), .down(decr), .diffOkArriv(diffOkArr), .diffOkDept(diffOkDept), .clk(clk), .reset(reset));

	assign diffOkArr = arrOutsideLvl[3:0] == insideLvl[3:0];
	assign diffOkDept = deptOutsideLvl[3:0] == insideLvl[3:0];
endmodule

lab2.1/adjustWater_testbench.v
`include "adjustWater.v"
module adjustWater_testbench();
	reg clk, reset, up, down;
	wire diffOkArr, diffOkDept;
	reg [3:0] arrOutsideLvl, deptOutsideLvl;
	wire [3:0] insideLvl;

	adjustWater dut(.insideLvl(insideLvl), .incr(up), .decr(down), .arrOutsideLvl(arrOutsideLvl), .deptOutsideLvl(deptOutsideLvl), .diffOkArr(diffOkArr), .diffOkDept(diffOkDept), .clk(clk), .reset(reset));

	// set up clock
	parameter CLOCK_PERIOD = 10; 
	initial clk = 1;

	always begin 
		#(CLOCK_PERIOD/2);
		clk = ~clk; 
	end

	initial begin
		$display("1.arrOutsideLvl 2.deptOutsideLvl 3.up, 4.down 5.insideWaterLvl, 6.diffOkArr, 7.diffOkDept");
		$monitor("%b\t %b\t  %b\t  %b\t %b\t %b\t %b\t", 
		         arrOutsideLvl, deptOutsideLvl, up, down, diffOkArr, diffOkDept);

		reset <= 1;															@(posedge clk);
		reset <= 0;															@(posedge clk);
					arrOutsideLvl <= 4'b0000;	deptOutsideLvl <= 4'b1101;	@(posedge clk);
																			@(posedge clk);
					up <= 1'b1;	down <= 1'b0;								@(posedge clk);
																			@(posedge clk);
																			@(posedge clk);
																			@(posedge clk);
																			@(posedge clk);
																			@(posedge clk);
																			@(posedge clk);
																			@(posedge clk);
																			@(posedge clk);
																			@(posedge clk);
																			@(posedge clk);
																			@(posedge clk);
																			@(posedge clk);
																			@(posedge clk);
																			@(posedge clk);
					up <= 1'b0;	down <= 1'b1;								@(posedge clk);
												arrOutsideLvl <= 4'b1000;	@(posedge clk);
																			@(posedge clk);
																			@(posedge clk);
																			@(posedge clk);
																			@(posedge clk);
																			@(posedge clk);
																			@(posedge clk);
																			@(posedge clk);
																			@(posedge clk);
																			@(posedge clk);
																			@(posedge clk);

		$finish; // finish simulation
	end


	// file for gtkwave
	initial begin
		// these two files support gtkwave and are required
		$dumpfile("adjustWater_testbench.vcd");
		$dumpvars;
	end
endmodule

lab2.1/adjustWater_testbench.vcd
$date
	Mon Oct 31 22:28:55 2016
$end
$version
	Icarus Verilog
$end
$timescale
	1s
$end
$scope module adjustWater_testbench $end
$var wire 4 ! insideLvl [3:0] $end
$var wire 1 " diffOkDept $end
$var wire 1 # diffOkArr $end
$var reg 4 $ arrOutsideLvl [3:0] $end
$var reg 1 % clk $end
$var reg 4 & deptOutsideLvl [3:0] $end
$var reg 1 ' down $end
$var reg 1 ( reset $end
$var reg 1 ) up $end
$scope module dut $end
$var wire 4 * arrOutsideLvl [3:0] $end
$var wire 1 % clk $end
$var wire 1 ' decr $end
$var wire 4 + deptOutsideLvl [3:0] $end
$var wire 1 ) incr $end
$var wire 1 ( reset $end
$var wire 4 , insideLvl [3:0] $end
$var wire 1 " diffOkDept $end
$var wire 1 # diffOkArr $end
$scope module counter $end
$var wire 1 % clk $end
$var wire 1 # diffOkArriv $end
$var wire 1 " diffOkDept $end
$var wire 1 ' down $end
$var wire 1 ( reset $end
$var wire 1 - start $end
$var wire 1 . stop $end
$var wire 1 ) up $end
$var wire 4 / out [3:0] $end
$var reg 1 0 enable $end
$var reg 4 1 val [3:0] $end
$upscope $end
$upscope $end
$upscope $end
$enddefinitions $end
#0
$dumpvars
bx 1
x0
bx /
x.
x-
bx ,
bx +
bx *
x)
1(
x'
bx &
1%
bx $
x#
x"
bx !
$end
#5
0%
#10
0(
00
b0 !
b0 ,
b0 /
b0 1
1%
#15
0%
#20
1.
0"
b1101 &
b1101 +
1#
b0 $
b0 *
1%
#25
0%
#30
1%
#35
0%
#40
1-
0'
1)
1%
#45
0%
#50
0.
0#
b1 !
b1 ,
b1 /
b1 1
10
1%
#55
0%
#60
b10 !
b10 ,
b10 /
b10 1
1%
#65
0%
#70
b11 !
b11 ,
b11 /
b11 1
1%
#75
0%
#80
b100 !
b100 ,
b100 /
b100 1
1%
#85
0%
#90
b101 !
b101 ,
b101 /
b101 1
1%
#95
0%
#100
b110 !
b110 ,
b110 /
b110 1
1%
#105
0%
#110
b111 !
b111 ,
b111 /
b111 1
1%
#115
0%
#120
b1000 !
b1000 ,
b1000 /
b1000 1
1%
#125
0%
#130
b1001 !
b1001 ,
b1001 /
b1001 1
1%
#135
0%
#140
b1010 !
b1010 ,
b1010 /
b1010 1
1%
#145
0%
#150
b1011 !
b1011 ,
b1011 /
b1011 1
1%
#155
0%
#160
b1100 !
b1100 ,
b1100 /
b1100 1
1%
#165
0%
#170
1.
1"
b1101 !
b1101 ,
b1101 /
b1101 1
1%
#175
0%
#180
00
1%
#185
0%
#190
0.
1'
0)
0"
b1110 !
b1110 ,
b1110 /
b1110 1
10
1%
#195
0%
#200
1.
1"
b1101 !
b1101 ,
b1101 /
b1101 1
b1000 $
b1000 *
1%
#205
0%
#210
00
1%
#215
0%
#220
0.
0"
b1100 !
b1100 ,
b1100 /
b1100 1
10
1%
#225
0%
#230
b1011 !
b1011 ,
b1011 /
b1011 1
1%
#235
0%
#240
b1010 !
b1010 ,
b1010 /
b1010 1
1%
#245
0%
#250
b1001 !
b1001 ,
b1001 /
b1001 1
1%
#255
0%
#260
1.
1#
b1000 !
b1000 ,
b1000 /
b1000 1
1%
#265
0%
#270
00
1%
#275
0%
#280
0.
0#
b111 !
b111 ,
b111 /
b111 1
10
1%
#285
0%
#290
b110 !
b110 ,
b110 /
b110 1
1%
#295
0%
#300
b101 !
b101 ,
b101 /
b101 1
1%
#305
0%
#310
b100 !
b100 ,
b100 /
b100 1
1%
