lab2.1/innerWaterLvl.v
module innerWaterLvl(out, enable, up, down, max, min, clk, reset);
	input enable, up, down, clk, reset;
	input [3:0] max, min;
	output [3:0] out;

	reg [3:0] ps, ns;

	always@(*) begin
		if (enable) begin
			if (up && ~down && (ps < max)) begin
				ns = ps + 1'b1;
			end else if (down && ~up && (ps > min)) begin
				ns = ps - 1'b1;
			end else begin
				ns = ps;
			end
		end else begin
			ns = ps;
		end
	end

	assign out = ps;

	always@(posedge clk) begin
		if (reset) begin
			ps <= 4'b0000;
		end else begin
			ps <= ns;
		end
	end
endmodule

lab2/innerWaterLvl_testbench.v
// EE371 Lab2 Autumn 2016
// authors: William Li, Dawn Liang, Jun Park
// date: 02 November 2016
// 
// testbench for innerWaterLvl module: tests normal operating conditions,
//   failure test cases include pressing up & down, disabled counter
`include "innerWaterLvl.v"
module innerWaterLvl_testbench();
	reg clk, reset, up, down, enable;
	reg [3:0] max, min;
	wire [3:0] out;

	// set up clock
	parameter CLOCK_PERIOD = 5;
	initial clk = 1;
	always begin
		#(CLOCK_PERIOD/2);
		clk = ~clk;
	end

	// connect I/Os
	innerWaterLvl dut (.out(out), .enable(enable), .up(up), .down(down), .max(max), .min(min), .clk(clk), .reset(reset));

	// run simulation
	initial begin
		reset <= 1;																			@(posedge clk);
		reset <= 0;	enable <= 0;	up <= 0;	down <= 0;	max <= 4'b0100;	min <= 4'b0001;	@(posedge clk);
									up <= 1;												@(posedge clk);
					enable <= 1;															@(posedge clk);
																							@(posedge clk);
																							@(posedge clk);
																							@(posedge clk);
																							@(posedge clk);
																							@(posedge clk);
									up <= 0;			down <= 1;							@(posedge clk);
																							@(posedge clk);
									up <= 1;												@(posedge clk);
									up <= 0;												@(posedge clk);
																							@(posedge clk);
																							@(posedge clk);
																							@(posedge clk);
		$finish;
	end

	// gtkwave filedump
	initial begin
		$dumpfile("innerWaterLvl.vcd");
		$dumpvars;
	end
endmodule

lab2.1/innerWaterLvl.vcd
$date
	Tue Nov  1 01:57:05 2016
$end
$version
	Icarus Verilog
$end
$timescale
	1s
$end
$scope module innerWaterLvl_testbench $end
$var wire 4 ! out [3:0] $end
$var reg 1 " clk $end
$var reg 1 # down $end
$var reg 1 $ enable $end
$var reg 4 % max [3:0] $end
$var reg 4 & min [3:0] $end
$var reg 1 ' reset $end
$var reg 1 ( up $end
$scope module dut $end
$var wire 1 " clk $end
$var wire 1 # down $end
$var wire 1 $ enable $end
$var wire 4 ) max [3:0] $end
$var wire 4 * min [3:0] $end
$var wire 4 + out [3:0] $end
$var wire 1 ' reset $end
$var wire 1 ( up $end
$var reg 4 , ns [3:0] $end
$var reg 4 - ps [3:0] $end
$upscope $end
$upscope $end
$enddefinitions $end
#0
$dumpvars
bx -
bx ,
bx +
bx *
bx )
x(
1'
bx &
bx %
x$
x#
1"
bx !
$end
#2
0"
#4
b0 ,
b1 &
b1 *
b100 %
b100 )
0#
0(
0$
0'
b0 !
b0 +
b0 -
1"
#6
0"
#8
1(
1"
#10
0"
#12
b1 ,
1$
1"
#14
0"
#16
b10 ,
b1 !
b1 +
b1 -
1"
#18
0"
#20
b11 ,
b10 !
b10 +
b10 -
1"
#22
0"
#24
b100 ,
b11 !
b11 +
b11 -
1"
#26
0"
#28
b100 !
b100 +
b100 -
1"
#30
0"
#32
1"
#34
0"
#36
b11 ,
1#
0(
1"
#38
0"
#40
b10 ,
b11 !
b11 +
b11 -
1"
#42
0"
#44
1(
b10 !
b10 +
b10 -
1"
#46
0"
#48
b1 ,
0(
1"
#50
0"
#52
b1 !
b1 +
b1 -
1"
