lab2.1/innerWaterLvl.v
module innerWaterLvl(out, enable, up, down, max, min, clk, reset);
	input enable, up, down, clk, reset;
	input [3:0] max, min;
	output [3:0] out;

	reg [3:0] ps, ns;

	always@(*) begin
		if (enable) begin
			if (up && ~down && (ps < max)) begin
				ns = ps + 1'b1;
			end else if (down && ~up && (ps > min)) begin
				ns = ps - 1'b1;
			end else begin
				ns = ps;
			end
		end else begin
			ns = ps;
		end
	end

	assign out = ps;

	always@(posedge clk) begin
		if (reset) begin
			ps <= 4'b0000;
		end else begin
			ps <= ns;
		end
	end
endmodule

lab2.1/poundOccupied.v
/*  EE 371 Lab 2
	Pound Occupied module 
	William Li, Jun Park, Dawn Liang

	poundOccupied module
*/

module poundOccupied(out, arrivalGate, departureGate, clk, reset);
	output out;
	input  arrivalGate, departureGate;
	input  clk, reset; 

	reg ps, ns; 

	always@(*) begin
		case (ps)
			0:	if (arrivalGate)
					ns = 1;
				else
					ns = 0;

			1:  if (departureGate)
					ns = 0;
				else
					ns = 1;
		endcase
	end

	assign out = ps; 

	always @(posedge clk) begin
		if (reset) begin
			ps <= 0;
		end else begin
			ps <= ns;
		end
	end
endmodule

lab2.1/gate.v
module gate(doorOpen, fiveMinTillArriv, diffOk, whatGate, poundOccu, ctrl, reset);
	output doorOpen;
	input fiveMinTillArriv, diffOk, whatGate, poundOccu, ctrl, reset;

	// add something to count to 5
	
	assign doorOpen = ctrl && ((~whatGate && diffOk) || (whatGate && diffOk && ~poundOccu && fiveMinTillArriv));
endmodule

lab2.1/clock_divider.v
module clock_divider #(parameter WHICH_CLOCK=5) (clk, divided_clock);
	input clk;
	output divided_clock;

	reg [31:0] clocks;
	initial clocks = 0;

	always@(posedge clk) begin
		clocks <= clocks + 1'b1;
	end

	assign divided_clock = clocks[WHICH_CLOCK];
endmodule

lab2.1/overall.v
`include "clock_divider.v"
`include "innerWaterLvl.v"
`include "gate.v"
`include "poundOccupied.v"
module overall(arrivGate, deptGate, insideWaterLvl, poundOccupied, incr, decr, arrivOutsideLvl, deptOutsideLvl, fiveMinTillArrival, gateCtrl, clock, reset);
	output [3:0] insideWaterLvl; // LEDs
	output arrivGate, deptGate; // LEDs
	output poundOccupied; // LED

	input [3:0] arrivOutsideLvl, deptOutsideLvl; // SWs
	input incr, decr, fiveMinTillArrival, gateCtrl; // KEYs
	input clock, reset; // internal, SW

	// clock divider
	clock_divider #(1) cDiv (clock, clk);

	// gates
	wire diffOkArr, diffOkDept;
	assign diffOkArr = (insideWaterLvl == arrivOutsideLvl);
	assign diffOkDept = (insideWaterLvl == deptOutsideLvl);
	gate arriv (.doorOpen(arrivGate), .fiveMinTillArriv(fiveMinTillArrival), .diffOk(diffOkArr), .whatGate(1'b1), .poundOccu(poundOccupied), .ctrl(gateCtrl), .reset(reset));
	gate dept (.doorOpen(deptGate), .fiveMinTillArriv(fiveMinTillArrival), .diffOk(diffOkDept), .whatGate(1'b0), .poundOccu(poundOccupied), .ctrl(gateCtrl), .reset(reset));

	// lock occupied
	poundOccupied occup(.out(poundOccupied), .arrivalGate(arrivGate), .departureGate(deptGate), .clk(clk), .reset(reset));

	wire doorOpen = arrivGate || deptGate;

	// controlling lock water levels
	reg [3:0] max, min;
	initial begin
		if (arrivOutsideLvl > deptOutsideLvl) begin
			assign max = arrivOutsideLvl;
			assign min = deptOutsideLvl;
		end else begin
			assign max = deptOutsideLvl;
			assign min = arrivOutsideLvl;
		end
	end

	innerWaterLvl inner (.out(insideWaterLvl), .enable(doorOpen), .up(incr), .down(decr), .max(max), .min(min), .clk(clk), .reset(reset));
endmodule

lab2.1/overall_testbench.v
`include "overall.v"
module overall_testbench();
	reg clk, reset;
	reg incr, decr, fiveMinTillArrival, gateCtrl;
	reg [3:0] arrivOutsideLvl, deptOutsideLvl;

	wire arrivGate, deptGate, poundOccupied;
	wire [3:0] insideWaterLvl;

	// connect I/Os
	overall dut (.arrivGate(arrivGate), .deptGate(deptGate), .insideWaterLvl(insideWaterLvl),
		.poundOccupied(poundOccupied), .incr(incr), .decr(decr),
		.arrivOutsideLvl(arrivOutsideLvl), .deptOutsideLvl(deptOutsideLvl),
		.fiveMinTillArrival(fiveMinTillArrival), .gateCtrl(gateCtrl), .clock(clk), .reset(reset));

	// set up clock
	parameter CLOCK_PERIOD = 5;
	initial clk = 1;
	always begin
		#(CLOCK_PERIOD/2);
		clk = ~clk;
	end

	// start simulation
	initial begin
		reset <= 1;														@(posedge clk);
																		@(posedge clk);
		reset <= 0;	arrivOutsideLvl <= 4'b0000; deptOutsideLvl <= 4'b0001;
					incr <= 0; decr <= 0;	fiveMinTillArrival <= 0; gateCtrl <= 0;	@(posedge clk);
											fiveMinTillArrival <= 1;	@(posedge clk);
																		@(posedge clk);
											gateCtrl <= 1;				@(posedge clk);
																		@(posedge clk);
											gateCtrl <= 0;				@(posedge clk);
					incr <= 1;											@(posedge clk);
																		@(posedge clk);
																		@(posedge clk);
																		@(posedge clk);
																		@(posedge clk);
																		@(posedge clk);
																		@(posedge clk);
																		@(posedge clk);
																		@(posedge clk);
																		@(posedge clk);
																		@(posedge clk);
																		@(posedge clk);
																		@(posedge clk);
		$finish;
	end

	// gtkwave filedump
	initial begin
		$dumpfile("overall.vcd");
		$dumpvars;
	end
endmodule

lab2.1/overall.vcd
$date
	Tue Nov  1 02:50:03 2016
$end
$version
	Icarus Verilog
$end
$timescale
	1s
$end
$scope module overall_testbench $end
$var wire 1 ! poundOccupied $end
$var wire 4 " insideWaterLvl [3:0] $end
$var wire 1 # deptGate $end
$var wire 1 $ arrivGate $end
$var reg 4 % arrivOutsideLvl [3:0] $end
$var reg 1 & clk $end
$var reg 1 ' decr $end
$var reg 4 ( deptOutsideLvl [3:0] $end
$var reg 1 ) fiveMinTillArrival $end
$var reg 1 * gateCtrl $end
$var reg 1 + incr $end
$var reg 1 , reset $end
$scope module dut $end
$var wire 4 - arrivOutsideLvl [3:0] $end
$var wire 1 & clock $end
$var wire 1 ' decr $end
$var wire 4 . deptOutsideLvl [3:0] $end
$var wire 1 / doorOpen $end
$var wire 1 ) fiveMinTillArrival $end
$var wire 1 * gateCtrl $end
$var wire 1 + incr $end
$var wire 1 , reset $end
$var wire 1 ! poundOccupied $end
$var wire 4 0 insideWaterLvl [3:0] $end
$var wire 1 1 diffOkDept $end
$var wire 1 2 diffOkArr $end
$var wire 1 # deptGate $end
$var wire 1 3 clk $end
$var wire 1 $ arrivGate $end
$var reg 4 4 max [3:0] $end
$var reg 4 5 min [3:0] $end
$scope module arriv $end
$var wire 1 * ctrl $end
$var wire 1 2 diffOk $end
$var wire 1 $ doorOpen $end
$var wire 1 ) fiveMinTillArriv $end
$var wire 1 , reset $end
$var wire 1 6 whatGate $end
$var wire 1 ! poundOccu $end
$upscope $end
$scope module cDiv $end
$var wire 1 & clk $end
$var wire 1 3 divided_clock $end
$var reg 32 7 clocks [31:0] $end
$upscope $end
$scope module dept $end
$var wire 1 * ctrl $end
$var wire 1 1 diffOk $end
$var wire 1 # doorOpen $end
$var wire 1 ) fiveMinTillArriv $end
$var wire 1 , reset $end
$var wire 1 8 whatGate $end
$var wire 1 ! poundOccu $end
$upscope $end
$scope module inner $end
$var wire 1 3 clk $end
$var wire 1 ' down $end
$var wire 1 / enable $end
$var wire 4 9 max [3:0] $end
$var wire 4 : min [3:0] $end
$var wire 1 , reset $end
$var wire 1 + up $end
$var wire 4 ; out [3:0] $end
$var reg 4 < ns [3:0] $end
$var reg 4 = ps [3:0] $end
$upscope $end
$scope module occup $end
$var wire 1 $ arrivalGate $end
$var wire 1 3 clk $end
$var wire 1 # departureGate $end
$var wire 1 , reset $end
$var wire 1 ! out $end
$var reg 1 > ns $end
$var reg 1 ! ps $end
$upscope $end
$upscope $end
$upscope $end
$enddefinitions $end
#0
$dumpvars
x>
bx =
bx <
bx ;
bx :
bx 9
08
b1 7
16
bx 5
bx 4
03
x2
x1
bx 0
x/
bx .
bx -
1,
x+
x*
x)
bx (
x'
1&
bx %
x$
x#
bx "
x!
$end
#2
0&
#4
0>
b0 <
0!
b0 "
b0 0
b0 ;
b0 =
13
b10 7
1&
#6
0&
#8
0/
0$
0#
b11 7
0*
0)
0'
0+
01
b1 4
b1 9
b1 (
b1 .
12
b0 5
b0 :
b0 %
b0 -
0,
1&
#10
0&
#12
03
1)
b100 7
1&
#14
0&
#16
b101 7
1&
#18
0&
#20
1>
1/
1$
13
1*
b110 7
1&
#22
0&
#24
b111 7
1&
#26
0&
#28
0>
0/
0$
03
0*
b1000 7
1&
#30
0&
#32
b1001 7
1+
1&
#34
0&
#36
13
b1010 7
1&
#38
0&
#40
b1011 7
1&
#42
0&
#44
03
b1100 7
1&
#46
0&
#48
b1101 7
1&
#50
0&
#52
13
b1110 7
1&
#54
0&
#56
b1111 7
1&
#58
0&
#60
03
b10000 7
1&
#62
0&
#64
b10001 7
1&
#66
0&
#68
13
b10010 7
1&
#70
0&
#72
b10011 7
1&
#74
0&
#76
03
b10100 7
1&
#78
0&
#80
b10101 7
1&
#82
0&
#84
13
b10110 7
1&
