lab2.1/poundOccupied.v
/*  EE 371 Lab 2
	Pound Occupied module 
	William Li, Jun Park, Dawn Liang

	poundOccupied module
*/

module poundOccupied(canalState, arrivalGate, departureGate, clk, reset);
	output canalState;
	input  arrivalGate;
	input  departureGate;
	input  clk;
	input  reset; 

	reg ps;
	reg ns; 

	parameter occupied = 1'b1, unoccupied = 1'b0;

	always@(*) begin
		case (ps)
			unoccupied: if (~arrivalGate && ~departureGate) ns = unoccupied;
						else if (arrivalGate && ~departureGate) ns = occupied;
						else ns = unoccupied;

			occupied:   if (~arrivalGate && ~departureGate) ns = occupied;
						else if (~arrivalGate && departureGate) ns = unoccupied;
						else ns = unoccupied;
		endcase
	end
	assign canalState = ps; 

	always @(posedge clk) begin
		if (reset) begin
			ps <= unoccupied;
		end else begin
			ps <= ns;
		end
	end
endmodule

lab2.1/gate.v
module gate(doorOpen, fiveMinTillArriv, diffOk, whatGate, poundOccu, reset);
	output doorOpen;
	input fiveMinTillArriv, diffOk, whatGate, poundOccu, reset;
	
	assign doorOpen = (~whatGate && poundOccu && diffOk) || (whatGate && diffOk && ~poundOccu && fiveMinTillArriv);	
endmodule

lab2.1/innerWaterLvl.v
module innerWaterLvl(out, enable, up, down, max, min, clk, reset);
	input enable, up, down, clk, reset;
	input [3:0] max, min;
	output [3:0] out;

	reg [3:0] ps, ns;

	always@(*) begin
		if (enable) begin
			if (up && ~down && (ps < max)) begin
				ns = ps + 1'b1;
			end else if (down && ~up && (ps > min)) begin
				ns = ps - 1'b1;
			end else begin
				ns = ps;
			end
		end else begin
			ns = ps;
		end
	end

	assign out = ps;

	always@(posedge clk) begin
		if (reset) begin
			ps <= 4'b0000;
		end else begin
			ps <= ns;
		end
	end
endmodule

lab2.1/clock_divider.v
module clock_divider #(parameter WHICH_CLOCK=5) (clk, divided_clock);
	input clk;
	output divided_clock;

	reg [31:0] clocks;
	initial clocks = 0;

	always@(posedge clk) begin
		clocks <= clocks + 1'b1;
	end

	assign divided_clock = clocks[WHICH_CLOCK];
endmodule

lab2.1/overall.v
`include "clock_divider.v"
`include "innerWaterLvl.v"
`include "gate.v"
`include "poundOccupied.v"
module overall(arrivGate, deptGate, insideWaterLvl, poundOccupied, incr, decr, arrivOutsideLvl, deptOutsideLvl, fiveMinTillArrival, clock, reset);
	output [3:0] insideWaterLvl; // LEDs
	output arrivGate, deptGate; // LEDs
	output poundOccupied; // LED

	input [3:0] arrivOutsideLvl, deptOutsideLvl; // SWs
	input incr, decr, fiveMinTillArrival; // KEYs
	input clock, reset; // internal, SW

	wire diffOkArr, diffOkDept;

	clock_divider #(24) cDiv (clock, clk);

	wire doorOpen = arrivGate || deptGate;

	reg [3:0] max, min;
	initial begin
		if (arrivOutsideLvl > deptOutsideLvl) begin
			assign max = arrivOutsideLvl;
			assign min = deptOutsideLvl;
		end else begin
			assign max = deptOutsideLvl;
			assign min = arrivOutsideLvl;
		end
	end

	innerWaterLvl inner (.out(insideWaterLvl), .enable(doorOpen), .up(incr), .down(decr), .max(max), .min(min), .clk(clk), .reset(reset));
	
	gate arriv(.doorOpen(arrivGate), .fiveMinTillArriv(fiveMinTillArrival), .diffOk(diffOkArr), .whatGate(1'b1), .poundOccu(poundOccupied), .reset(reset));
	gate dept(.doorOpen(deptGate), .fiveMinTillArriv(fiveMinTillArrival), .diffOk(diffOkDept), .whatGate(1'b0), .poundOccu(poundOccupied), .reset(reset));

	poundOccupied occup(.canalState(poundOccupied), .arrivalGate(arrivGate), .departureGate(deptGate), .clk(clk), .reset(reset));
endmodule

lab2.1/overall_testbench.v
`include "overall.v"
module overall_testbench();
	reg clk, reset;
	reg incr, decr, fiveMinTillArrival;
	reg [3:0] arrivOutsideLvl, deptOutsideLvl;

	wire arrivGate, deptGate, poundOccupied;
	wire [3:0] insideWaterLvl;

	// connect I/Os
	overall dut (.arrivGate(arrivGate), .deptGate(deptGate), .insideWaterLvl(insideWaterLvl),
		.poundOccupied(poundOccupied), .incr(incr), .decr(decr),
		.arrivOutsideLvl(arrivOutsideLvl), .deptOutsideLvl(deptOutsideLvl),
		.fiveMinTillArrival(fiveMinTillArrival), .clock(clk), .reset(reset));

	// set up clock
	parameter CLOCK_PERIOD = 5;
	initial clk = 1;
	always begin
		#(CLOCK_PERIOD/2);
		clk = ~clk;
	end

	// start simulation
	initial begin
		reset <= 1;														@(posedge clk);
		reset <= 0;	arrivOutsideLvl <= 4'b0100; deptOutsideLvl <= 4'b0001;
					incr <= 0; decr <= 0;	fiveMinTillArrival <= 0;	@(posedge clk);
											fiveMinTillArrival <= 1;	@(posedge clk);
																		@(posedge clk);
																		@(posedge clk);
																		@(posedge clk);
					incr <= 1;											@(posedge clk);
																		@(posedge clk);
																		@(posedge clk);
																		@(posedge clk);
		$finish;
	end

	// gtkwave filedump
	initial begin
		$dumpfile("overall.vcd");
		$dumpvars;
	end
endmodule

lab2.1/overall.vcd
$date
	Tue Nov  1 01:59:56 2016
$end
$version
	Icarus Verilog
$end
$timescale
	1s
$end
$scope module overall_testbench $end
$var wire 1 ! poundOccupied $end
$var wire 4 " insideWaterLvl [3:0] $end
$var wire 1 # deptGate $end
$var wire 1 $ arrivGate $end
$var reg 4 % arrivOutsideLvl [3:0] $end
$var reg 1 & clk $end
$var reg 1 ' decr $end
$var reg 4 ( deptOutsideLvl [3:0] $end
$var reg 1 ) fiveMinTillArrival $end
$var reg 1 * incr $end
$var reg 1 + reset $end
$scope module dut $end
$var wire 4 , arrivOutsideLvl [3:0] $end
$var wire 1 & clock $end
$var wire 1 ' decr $end
$var wire 4 - deptOutsideLvl [3:0] $end
$var wire 1 . diffOkArr $end
$var wire 1 / diffOkDept $end
$var wire 1 0 doorOpen $end
$var wire 1 ) fiveMinTillArrival $end
$var wire 1 * incr $end
$var wire 1 + reset $end
$var wire 1 ! poundOccupied $end
$var wire 4 1 insideWaterLvl [3:0] $end
$var wire 1 # deptGate $end
$var wire 1 2 clk $end
$var wire 1 $ arrivGate $end
$var reg 4 3 max [3:0] $end
$var reg 4 4 min [3:0] $end
$scope module arriv $end
$var wire 1 . diffOk $end
$var wire 1 $ doorOpen $end
$var wire 1 ) fiveMinTillArriv $end
$var wire 1 + reset $end
$var wire 1 5 whatGate $end
$var wire 1 ! poundOccu $end
$upscope $end
$scope module cDiv $end
$var wire 1 & clk $end
$var wire 1 2 divided_clock $end
$var reg 32 6 clocks [31:0] $end
$upscope $end
$scope module dept $end
$var wire 1 / diffOk $end
$var wire 1 # doorOpen $end
$var wire 1 ) fiveMinTillArriv $end
$var wire 1 + reset $end
$var wire 1 7 whatGate $end
$var wire 1 ! poundOccu $end
$upscope $end
$scope module inner $end
$var wire 1 2 clk $end
$var wire 1 ' down $end
$var wire 1 0 enable $end
$var wire 4 8 max [3:0] $end
$var wire 4 9 min [3:0] $end
$var wire 4 : out [3:0] $end
$var wire 1 + reset $end
$var wire 1 * up $end
$var reg 4 ; ns [3:0] $end
$var reg 4 < ps [3:0] $end
$upscope $end
$scope module occup $end
$var wire 1 $ arrivalGate $end
$var wire 1 2 clk $end
$var wire 1 # departureGate $end
$var wire 1 + reset $end
$var wire 1 ! canalState $end
$var reg 1 = ns $end
$var reg 1 ! ps $end
$upscope $end
$upscope $end
$upscope $end
$enddefinitions $end
#0
$dumpvars
x=
bx <
bx ;
bx :
bx 9
bx 8
07
b1 6
15
bx 4
bx 3
02
bx 1
x0
z/
z.
bx -
bx ,
1+
x*
x)
bx (
x'
1&
bx %
x$
x#
bx "
x!
$end
#2
0&
#4
0$
0)
0'
0*
b1 3
b1 8
b1 (
b1 -
b100 4
b100 9
b100 %
b100 ,
0+
b10 6
1&
#6
0&
#8
x$
b11 6
1)
1&
#10
0&
#12
b100 6
1&
#14
0&
#16
b101 6
1&
#18
0&
#20
b110 6
1&
#22
0&
#24
b111 6
1*
1&
#26
0&
#28
b1000 6
1&
#30
0&
#32
b1001 6
1&
#34
0&
#36
b1010 6
1&
#38
0&
#40
b1011 6
1&
